Workbook

Sheet Main_
A1: Категория | B1: Активы | C1: 01.10.2022 | D1: 01.11.2022 | E1: 01.12.2022 | F1: 01.01.2023 | G1: 01.02.2023 | H1: 01.03.2023 | I1: 01.04.2023 | J1: 01.05.2023 | K1: 01.06.2023 | L1: 01.07.2023 | M1: 01.08.2023 | N1: 01.09.2023 | O1: 01.10.2023 | P1: 01.11.2023 | Q1: 01.12.2023 | R1: 01.01.2024 | S1: 01.02.2024 | T1: 01.03.2024 | U1: 01.04.2024 | V1: 01.05.2024 | W1: 01.06.2024 | X1: 01.07.2024 | Y1: 01.08.2024 | Z1: 01.09.2024 | AA1: 01.10.2024 | AB1: 01.11.2024 | AC1: 01.12.2024 | AD1: 01.01.2025 | AE1: 01.02.2025 | AF1: 01.03.2025 | AG1: 01.04.2025 | AH1: 01.05.2025 | AI1: 01.06.2025 | AJ1: 01.07.2025 | AK1: 01.08.2025 | AL1: 01.09.2025 | AM1: 01.10.2025 | AN1: 01.11.2025 | AO1: 01.12.2025 | AP1: 01.01.2026 | AQ1: 01.02.2026 | AR1: 01.03.2026 | AS1: 01.04.2026 | AT1: 01.05.2026 | AU1: 01.06.2026 | AV1: MtM | AW1: YtY
A2: Счета в ЦБ РФ | B2: Евро, млн | C2: 49188.8 | D2: 45733.5 | E2: 41891.7 | F2: 10464.5 | G2: 10464.5 | H2: 10464.5 | I2: 10398.8 | J2: 9233.6 | K2: 9054.6 | L2: 7278.7 | M2: 7278.7 | N2: 5224.6 | O2: 4070.6 | P2: 3666.6 | Q2: 3268.8 | R2: 0 | S2: 0 | T2: 0 | U2: 0 | V2: 0 | W2: 0 | X2: 0 | Y2: 0 | Z2: 0 | AA2: 0 | AB2: 0 | AC2: 0 | AD2: 0 | AE2: 0 | AF2: 0 | AG2: 0 | AH2: 0 | AI2: 0 | AJ2: 0 | AK2: 0 | AL2: 0 | AM2: 0 | AN2: 0 | AO2: 0 | AP2: 0 | AQ2: 0 | AR2: 0 | AS2: 0 | AT2: 0 | AU2: 0 | AV2: =AU2-AT2 -> 0 | AW2: =AU2-AI2 -> 0
A3: Счета в ЦБ РФ | B3: Фунты стерлингов, млн | C3: 5313.3 | D3: 4938.3 | E3: 2769.6 | F3: 0 | G3: 0 | H3: 0 | I3: 0 | J3: 0 | K3: 0 | L3: 0 | M3: 0 | N3: 0 | O3: 0 | P3: 0 | Q3: 0 | R3: 0 | S3: 0 | T3: 0 | U3: 0 | V3: 0 | W3: 0 | X3: 0 | Y3: 0 | Z3: 0 | AA3: 0 | AB3: 0 | AC3: 0 | AD3: 0 | AE3: 0 | AF3: 0 | AG3: 0 | AH3: 0 | AI3: 0 | AJ3: 0 | AK3: 0 | AL3: 0 | AM3: 0 | AN3: 0 | AO3: 0 | AP3: 0 | AQ3: 0 | AR3: 0 | AS3: 0 | AT3: 0 | AU3: 0 | AV3: =AU3-AT3 -> 0 | AW3: =AU3-AI3 -> 0
A4: Счета в ЦБ РФ | B4: Японские йены, млн | C4: 768257.7 | D4: 692698.4 | E4: 478478.3 | F4: 0 | G4: 0 | H4: 0 | I4: 0 | J4: 0 | K4: 0 | L4: 0 | M4: 0 | N4: 0 | O4: 0 | P4: 0 | Q4: 0 | R4: 0 | S4: 0 | T4: 0 | U4: 0 | V4: 0 | W4: 0 | X4: 0 | Y4: 0 | Z4: 0 | AA4: 0 | AB4: 0 | AC4: 0 | AD4: 0 | AE4: 0 | AF4: 0 | AG4: 0 | AH4: 0 | AI4: 0 | AJ4: 0 | AK4: 0 | AL4: 0 | AM4: 0 | AN4: 0 | AO4: 0 | AP4: 0 | AQ4: 0 | AR4: 0 | AS4: 0 | AT4: 0 | AU4: 0 | AV4: =AU4-AT4 -> 0 | AW4: =AU4-AI4 -> 0
A5: Счета в ЦБ РФ | B5: Китайский юань, млн | C5: 309720.1 | D5: 309720.1 | E5: 309720.1 | F5: 309720.1 | G5: 307445.9 | H5: 300067.9 | I5: 292588.8 | J5: 288330.1 | K5: 285736.1 | L5: 282284.2 | M5: 280158.9 | N5: 279773.7 | O5: 279773.7 | P5: 279773.7 | Q5: 279773.7 | R5: 227330.7 | S5: 227517.1 | T5: 227517.1 | U5: 227615.8 | V5: 227615.8 | W5: 227615.8 | X5: 229532.6 | Y5: 226532.6 | Z5: 223782.6 | AA5: 221782.6 | AB5: 220532.6 | AC5: 219532.6 | AD5: 164044.2 | AE5: 164255.8 | AF5: 164285.9 | AG5: 164387.6 | AH5: 164597.2 | AI5: 153698.1 | AJ5: 214820.7 | AK5: 210208.6 | AL5: 209152 | AM5: 209152 | AN5: =AM5 -> 209152 | AO5: =AN5 -> 209152 | AP5: =AO5 -> 209152 | AQ5: 201065.7 | AR5: 188087.1 | AS5: 185210.6 | AT5: 185210.6 | AU5: 185546.9 | AV5: =AU5-AT5 -> 336.3 | AW5: =AU5-AI5 -> 31848.8
A6: Счета в ЦБ РФ | B6: Золото (обезличенное), кг | C6: 554910.5 | D6: 554910.5 | E6: 554910.5 | F6: 554910.5 | G6: 551277.5 | H6: 539245.1 | I6: 527382.3 | J6: 520974 | K6: 517114.1 | L6: 511986.9 | M6: 508835.4 | N6: 508265.3 | O6: 508265.3 | P6: 508265.3 | Q6: 508265.3 | R6: 358960.6 | S6: 358960.6 | T6: 358014.6 | U6: 334863.2 | V6: 334367.3 | W6: 329705.3 | X6: 303578.6 | Y6: 298840.4 | Z6: 293188.6 | AA6: 292494.1 | AB6: 283575.3 | AC6: 279562.6 | AD6: 187749.1 | AE6: 178996 | AF6: 174626.7 | AG6: 168271.4 | AH6: 168061.1 | AI6: 139509.1 | AJ6: 211953.9 | AK6: 179097.4 | AL6: 178260.9 | AM6: 173109.6 | AN6: 173102.6 | AO6: 173039.4 | AP6: 160241.2 | AQ6: 155093.7 | AR6: 147197.2 | AS6: 145348.4 | AT6: 145180.1 | AU6: 145180.1 | AV6: =AU6-AT6 -> 0 | AW6: =AU6-AI6 -> 5671
A7: Счета в ЦБ РФ | B7: Рубли, млн | C7: 264.3 | D7: 526.7 | E7: 242.7 | F7: 274.8 | G7: 530.1 | H7: 6124 | I7: 140.7 | J7: 232.8 | K7: 228 | L7: 400.4 | M7: 5490.5 | N7: 6775.9 | O7: 395.9 | P7: 261.8 | Q7: 1187.6 | R7: 1514 | S7: 294.8 | T7: 1241 | U7: 1650.1 | V7: 299.7 | W7: 1252 | X7: 1676 | Y7: 368.5 | Z7: 1261.9 | AA7: 1612.3 | AB7: 410.2 | AC7: 1429.9 | AD7: 1630.9 | AE7: 0 | AF7: 1249.6 | AG7: 1671.6 | AH7: 397.6 | AI7: 1271.3 | AJ7: 2525.5 | AK7: 419.6 | AL7: 1267.4 | AM7: 473.7 | AN7: 0 | AO7: 1734.4 | AP7: 3123 | AQ7: 0 | AR7: 1295.9 | AS7: 2936.3 | AT7: 1320.8 | AU7: 1534 | AV7: =AU7-AT7 -> 213.2 | AW7: =AU7-AI7 -> 262.7
A8: Депозиты и субординированные депозиты в ВЭБ.РФ | B8: Финансирование приобретения ВЭБ.РФ акций ГПБ, млн. руб** | G8: 50000 | L8: 50000 | M8: 50000 | N8: 50000 | O8: 50000 | P8: =O8 -> 50000 | Q8: 50000 | R8: =Q8 -> 50000 | S8: =R8 -> 50000 | T8: 50000 | U8: =T8 -> 50000 | V8: =U8 -> 50000 | W8: =V8 -> 50000 | X8: =W8 -> 50000 | Y8: =X8 -> 50000 | Z8: =Y8 -> 50000 | AA8: =Z8 -> 50000 | AB8: =AA8 -> 50000 | ... AG8: =AF8 -> 50000 | AH8: 50000 | AI8: =AH8 -> 50000 | AJ8: =AI8 -> 50000 | AK8: =AJ8 -> 50000 | AL8: =AK8 -> 50000 | AM8: =AL8 -> 50000 | AN8: =AM8 -> 50000 | AO8: =AN8 -> 50000 | AP8: =AO8 -> 50000 | ... AU8: =AT8 -> 50000 | AV8: =AU8-AT8 -> 0 | AW8: =AU8-AI8 -> 0
A9: Депозиты и субординированные депозиты в ВЭБ.РФ | B9: Кредитование субъектов малого и среднего предпринимательства, млн.руб | G9: 30000 | L9: 30000 | M9: 30000 | N9: 30000 | O9: 30000 | P9: =O9 -> 30000 | Q9: 30000 | R9: =Q9 -> 30000 | S9: =R9 -> 30000 | T9: =S9 -> 30000 | U9: =T9 -> 30000 | V9: =U9 -> 30000 | W9: =V9 -> 30000 | X9: =W9 -> 30000 | Y9: =X9 -> 30000 | ... AG9: =AF9 -> 30000 | AH9: 30000 | AI9: =AH9 -> 30000 | AJ9: =AI9 -> 30000 | AK9: =AJ9 -> 30000 | AL9: =AK9 -> 30000 | AM9: =AL9 -> 30000 | AN9: =AM9 -> 30000 | AO9: =AN9 -> 30000 | AP9: =AO9 -> 30000 | ... AU9: =AT9 -> 30000 | AV9: =AU9-AT9 -> 0 | AW9: =AU9-AI9 -> 0
A10: Депозиты и субординированные депозиты в ВЭБ.РФ | B10: Кредитование АО ДОМ.РФ, млн. руб | G10: 40000 | L10: 40000 | M10: 40000 | N10: 40000 | O10: 40000 | P10: =O10 -> 40000 | Q10: 40000 | R10: =Q10 -> 40000 | S10: =R10 -> 40000 | T10: =S10 -> 40000 | U10: =T10 -> 40000 | V10: =U10 -> 40000 | W10: =V10 -> 40000 | X10: =W10 -> 40000 | Y10: =X10 -> 40000 | ... AG10: =AF10 -> 40000 | AH10: 40000 | AI10: =AH10 -> 40000 | AJ10: =AI10 -> 40000 | AK10: =AJ10 -> 40000 | AL10: =AK10 -> 40000 | AM10: =AL10 -> 40000 | AN10: =AM10 -> 40000 | AO10: =AN10 -> 40000 | AP10: =AO10 -> 40000 | ... AU10: =AT10 -> 40000 | AV10: =AU10-AT10 -> 0 | AW10: =AU10-AI10 -> 0
A11: Депозиты и субординированные депозиты в ВЭБ.РФ | B11: Обеспечение достаточности собственных средств (капитала) ВЭБ.РФ, млн. руб | G11: 138830 | L11: 138830 | M11: 138830 | N11: 138830 | O11: 138830 | P11: =O11 -> 138830 | Q11: 138830 | R11: =Q11 -> 138830 | S11: =R11 -> 138830 | T11: =S11 -> 138830 | U11: =T11 -> 138830 | V11: =U11 -> 138830 | W11: =V11 -> 138830 | X11: =W11 -> 138830 | Y11: =X11 -> 138830 | ... AG11: =AF11 -> 138830 | AH11: 138830 | AI11: =AH11 -> 138830 | AJ11: =AI11 -> 138830 | AK11: =AJ11 -> 138830 | AL11: =AK11 -> 138830 | AM11: =AL11 -> 138830 | AN11: =AM11 -> 138830 | AO11: =AN11 -> 138830 | AP11: =AO11 -> 138830 | ... AU11: =AT11 -> 138830 | AV11: =AU11-AT11 -> 0 | AW11: =AU11-AI11 -> 0
A12: Депозиты и субординированные депозиты в ВЭБ.РФ | B12: Обеспечение достаточности собственных средств (капитала) ВЭБ.РФ, млн. руб | G12: 197580 | L12: 197580 | M12: 197580 | N12: 197580 | O12: 197580 | P12: =O12 -> 197580 | Q12: 197580 | R12: =Q12 -> 197580 | S12: =R12 -> 197580 | T12: =S12 -> 197580 | U12: =T12 -> 197580 | V12: =U12 -> 197580 | W12: =V12 -> 197580 | X12: =W12 -> 197580 | Y12: =X12 -> 197580 | ... AG12: =AF12 -> 197580 | AH12: 197580 | AI12: =AH12 -> 197580 | AJ12: =AI12 -> 197580 | AK12: =AJ12 -> 197580 | AL12: =AK12 -> 197580 | AM12: =AL12 -> 197580 | AN12: =AM12 -> 197580 | AO12: =AN12 -> 197580 | AP12: =AO12 -> 197580 | ... AU12: =AT12 -> 197580 | AV12: =AU12-AT12 -> 0 | AW12: =AU12-AI12 -> 0
A13: Депозиты и субординированные депозиты в ВЭБ.РФ | B13: Не регламентировано (обкспечение достаточности ВЭБ.РФ), млн. руб | G13: 16240 | L13: 16240 | M13: 16240 | N13: 16240 | O13: 16240 | P13: =O13 -> 16240 | Q13: 16240 | R13: =Q13 -> 16240 | S13: =R13 -> 16240 | T13: =S13 -> 16240 | U13: =T13 -> 16240 | V13: =U13 -> 16240 | W13: =V13 -> 16240 | X13: =W13 -> 16240 | Y13: =X13 -> 16240 | ... AU13: =AT13 -> 16240 | AV13: =AU13-AT13 -> 0 | AW13: =AU13-AI13 -> 0
A14: Депозиты и субординированные депозиты в ВЭБ.РФ | B14: Проект Лизинг вагонов Московского метро (КЖЦ-1), млн. руб | G14: 18350 | L14: 17660 | M14: =L14-139.8 -> 17520.2 | N14: 17390 | O14: =17250-0.7 -> 17249.3 | P14: =O14-142.9 -> 17106.4 | Q14: 16980 | R14: =Q14-145 -> 16835 | S14: =R14-142.2 -> 16692.8 | T14: =S14-143.4 -> 16549.4 | U14: =T14-152.6 -> 16396.8 | V14: =U14-145.6 -> 16251.2 | W14: =V14-150.7 -> 16100.5 | X14: =W14-147.9 -> 15952.6 | Y14: =X14-152.9 -> 15799.7 | Z14: =Y14-150.2 -> 15649.5 | AA14: =Z14-151.3 -> 15498.2 | AB14: =AA14-156.3 -> 15341.9 | AC14: =AB14-153.7 -> 15188.2 | AD14: =AC14-158.6 -> 15029.6 | AE14: =AD14-155.8 -> 14873.8 | AF14: =AE14-156.9 -> 14716.9 | AG14: =AF14-169 -> 14547.9 | AH14: =AG14-159.4 -> 14388.5 | AI14: =AH14-164.2 -> 14224.3 | AJ14: =AI14-161.9 -> 14062.4 | AK14: =AJ14-166.6 -> 13895.8 | AL14: =AK14-164.4 -> 13731.4 | AM14: =AL14-165.6 -> 13565.8 | AN14: =AM14-170.3 -> 13395.5 | AO14: =AN14-168.2 -> 13227.3 | AP14: =AO14-172.8 -> 13054.5 | AQ14: =AP14-170.8 -> 12883.7 | AR14: =AQ14-172.1 -> 12711.6 | AS14: =AR14-182.8 -> 12528.8 | AT14: =AS14-174.8 -> 12354 | AU14: =AT14-179.2 -> 12174.8 | AV14: =AU14-AT14 -> -179.2 | AW14: =AU14-AI14 -> -2049.5
A15: Депозиты и субординированные депозиты в ВЭБ.РФ | B15: Проект Строительство нового аэропортового комплекса Центральный (г. Саратов), млн. руб | G15: 4830 | L15: 4550 | M15: 4550 | N15: 4550 | O15: 4410 | P15: =O15 -> 4410 | Q15: 4410 | R15: =Q15-140.7 -> 4269.3 | S15: =R15 -> 4269.3 | T15: =S15 -> 4269.3 | U15: =T15-140.7 -> 4128.6 | V15: =U15 -> 4128.6 | W15: =V15 -> 4128.6 | X15: =W15-140.7 -> 3987.9 | Y15: =X15 -> 3987.9 | Z15: =Y15 -> 3987.9 | AA15: =Z15-140.7 -> 3847.2 | AB15: =AA15 -> 3847.2 | AC15: =AB15 -> 3847.2 | AD15: =AC15-140.7 -> 3706.5 | AE15: =AD15 -> 3706.5 | AF15: =AE15 -> 3706.5 | AG15: =AF15-166.7 -> 3539.8 | AH15: =AG15 -> 3539.8 | AI15: =AH15 -> 3539.8 | AJ15: =AI15-166.7 -> 3373.1 | AK15: =AJ15 -> 3373.1 | AL15: =AK15 -> 3373.1 | AM15: =AL15-166.7 -> 3206.4 | AN15: =AM15 -> 3206.4 | AO15: =AN15 -> 3206.4 | AP15: =AO15-166.7 -> 3039.7 | AQ15: =AP15 -> 3039.7 | AR15: =AQ15 -> 3039.7 | AS15: =AR15-166.7 -> 2873 | AT15: =AS15 -> 2873 | AU15: =AT15 -> 2873 | AV15: =AU15-AT15 -> 0 | AW15: =AU15-AI15 -> -666.8
A16: Депозиты и субординированные депозиты в ВЭБ.РФ | B16: Проект Лизинг вагонов Московского метро (КЖЦ-2), млн. руб | G16: 31590 | L16: 31030 | M16: =L16-115.3 -> 30914.7 | N16: 30820 | O16: 30700 | P16: =O16-118.9 -> 30581.1 | Q16: 30470 | R16: =Q16-121.4 -> 30348.6 | S16: =R16-90.4 -> 30258.2 | T16: =S16-158.8 -> 30099.4 | U16: =T16-167.3 -> 29932.1 | V16: =U16-154.1 -> 29778 | W16: =V16-162.4 -> 29615.6 | X16: =W16-156.5 -> 29459.1 | Y16: =X16-150.6 -> 29308.5 | Z16: =Y16-172.9 -> 29135.6 | AA16: =Z16-160.1 -> 28975.5 | AB16: =AA16-161.2 -> 28814.3 | AC16: =AB16-169.4 -> 28644.9 | AD16: =AC16-170.6 -> 28474.3 | AE16: =AD16-164.5 -> 28309.8 | AF16: =AE16-153.8 -> 28156 | AG16: =AF16-173.9 -> 27982.1 | AH16: =AG16-142 -> 27840.1 | AI16: =AH16-168.2 -> 27671.9 | AJ16: =AI16-153.2 -> 27518.7 | AK16: =AJ16-154.6 -> 27364.1 | AL16: =AK16-164.2 -> 27199.9 | AM16: =AL16-141.3 -> 27058.6 | AN16: =AM16-183.1 -> 26875.5 | AO16: =AN16-160.5 -> 26715 | AP16: =AO16-154.1 -> 26560.9 | AQ16: =AP16-179.3 -> 26381.6 | AR16: =AQ16-184.9 -> 26196.7 | AS16: =AR16-215.2 -> 25981.5 | AT16: =AS16-201.5 -> 25780 | AU16: =AT16-207.6 -> 25572.4 | AV16: =AU16-AT16 -> -207.6 | AW16: =AU16-AI16 -> -2099.5
A17: Депозиты и субординированные депозиты в ВЭБ.РФ | B17: Проект комплекса наземного электрического транспорта в Нижнем Новгороде, млн. руб | O17: 0 | P17: 154.9 | Q17: 154.9 | R17: =Q17 -> 154.9 | S17: =R17 -> 154.9 | T17: =S17 -> 154.9 | U17: =T17 -> 154.9 | V17: =U17 -> 154.9 | W17: =V17 -> 154.9 | X17: =W17 -> 154.9 | Y17: =X17 -> 154.9 | ... AO17: =AN17 -> 154.9 | AP17: =AO17+1658.3 -> 1813.2 | AQ17: =AP17 -> 1813.2 | AR17: =AQ17 -> 1813.2 | AS17: =AR17+574.3 -> 2387.5 | AT17: =AS17 -> 2387.5 | AU17: =AT17 -> 2387.5 | AV17: =AU17-AT17 -> 0 | AW17: =AU17-AI17 -> 2232.6
A18: Депозиты и субординированные депозиты в ВЭБ.РФ | B18: Проект комплекса наземного электрического транспорта в Курске, млн. руб | Y18: 300.5 | Z18: =Y18 -> 300.5 | AA18: =Z18 -> 300.5 | AB18: =AA18 -> 300.5 | AC18: =AB18 -> 300.5 | AD18: =AC18 -> 300.5 | AE18: =AD18 -> 300.5 | AF18: =AE18 -> 300.5 | AG18: =AF18 -> 300.5 | ... AJ18: =AI18 -> 300.5 | AK18: =AJ18-2.7 -> 297.8 | AL18: =AK18 -> 297.8 | AM18: =AL18 -> 297.8 | AN18: =AM18-2.7 -> 295.1 | AO18: =AN18-26.5 -> 268.6 | AP18: =AO18 -> 268.6 | AQ18: =AP18-29.5 -> 239.1 | AR18: =AQ18 -> 239.1 | AS18: =AR18 -> 239.1 | AT18: =AS18-30.9 -> 208.2 | AU18: =AT18 -> 208.2 | AV18: =AU18-AT18 -> 0 | AW18: =AU18-AI18 -> -92.3
A19: Депозиты и субординированные депозиты в ВЭБ.РФ | B19: Проект комплекса наземного электрического транспорта в Липецке, млн. руб | Y19: 939.5 | Z19: =Y19 -> 939.5 | AA19: =Z19 -> 939.5 | AB19: =AA19 -> 939.5 | AC19: =AB19 -> 939.5 | AD19: =AC19 -> 939.5 | AE19: =AD19 -> 939.5 | AF19: =AE19 -> 939.5 | AG19: =AF19 -> 939.5 | ... AS19: =AR19 -> 939.5 | AT19: =AS19-54.2 -> 885.3 | AU19: =AT19 -> 885.3 | AV19: =AU19-AT19 -> 0 | AW19: =AU19-AI19 -> -54.2
A20: Депозиты и субординированные депозиты в ВЭБ.РФ | B20: Проект комплекса наземного электрического транспорта в Ярославле, млн. руб | AR20: 523.9 | AS20: =AR20 -> 523.9 | AT20: =AS20 -> 523.9 | AU20: =AT20 -> 523.9 | AV20: =AU20-AT20 -> 0 | AW20: =AU20-AI20 -> 523.9
A21: Депозиты и субординированные депозиты в ВЭБ.РФ | B21: Проект Обновление подвижного состава ГУП Петербургский метрополитен, млн. руб | G21: 2170 | L21: 7130 | M21: =L21+2405.9 -> 9535.9 | N21: 11170 | O21: 12020 | P21: =O21+842.4 -> 12862.4 | Q21: 13700 | R21: =Q21+870.5 -> 14570.5 | S21: =R21 -> 14570.5 | T21: =S21 -> 14570.5 | U21: =T21 -> 14570.5 | V21: =U21+1786.7 -> 16357.2 | W21: =V21+893.3 -> 17250.5 | X21: =W21+917.7 -> 18168.2 | Y21: =X21+917.7 -> 19085.9 | Z21: =Y21+917.7 -> 20003.6 | AA21: =Z21+938 -> 20941.6 | AB21: =AA21 -> 20941.6 | AC21: =AB21 -> 20941.6 | AD21: =AC21+2832.8 -> 23774.4 | AE21: =AD21 -> 23774.4 | AF21: =AE21 -> 23774.4 | AG21: =AF21 -> 23774.4 | AH21: =AG21+1950.2 -> 25724.6 | AI21: =AH21+975.1 -> 26699.7 | AJ21: =AI21+995.7 -> 27695.4 | AK21: =AJ21+995.7 -> 28691.1 | AL21: =AK21+995.7 -> 29686.8 | AM21: =AL21+991.7 -> 30678.5 | AN21: =AM21+991.7 -> 31670.2 | AO21: =AN21+1983.4 -> 33653.6 | AP21: =AO21+3950.9 -> 37604.5 | AQ21: =AP21+987.7 -> 38592.2 | AR21: =AQ21 -> 38592.2 | AS21: =AR21 -> 38592.2 | AT21: =AS21+3028.7-692.2 -> 40928.7 | AU21: =AT21+757.2 -> 41685.9 | AV21: =AU21-AT21 -> 757.2 | AW21: =AU21-AI21 -> 14986.2
A22: Депозиты и субординированные депозиты в ВЭБ.РФ | B22: Проект транспортной инфраструктуры в Краснодаре, млн. руб | AN22: 461.6 | AO22: =AN22 -> 461.6 | AP22: =AO22 -> 461.6 | AQ22: =AP22-2 -> 459.6 | AR22: =AQ22 -> 459.6 | AS22: =AR22 -> 459.6 | AT22: =AS22-2 -> 457.6 | AU22: =AT22 -> 457.6 | AV22: =AU22-AT22 -> 0 | AW22: =AU22-AI22 -> 457.6
A23: Депозиты и субординированные депозиты в ВЭБ.РФ | B23: Проект Комплекс по переработке этансодержащего газа в п. Усть-Луга (Субординировванный депозит) | V23: 316 | W23: =V23 -> 316 | X23: =W23 -> 316 | Y23: =X23+26885 -> 27201 | Z23: =Y23 -> 27201 | AA23: =Z23 -> 27201 | AB23: =AA23+62050 -> 89251 | AC23: =AB23 -> 89251 | AD23: =AC23+137039 -> 226290 | AE23: =AD23+77848 -> 304138 | AF23: =AE23+37297 -> 341435 | AG23: =AF23+49015 -> 390450 | AH23: =AG23 -> 390450 | AI23: =AH23+47473 -> 437923 | AJ23: =AI23 -> 437923 | AK23: =AJ23 -> 437923 | AL23: =AK23 -> 437923 | AM23: =AL23 -> 437923 | AN23: =AM23 -> 437923 | AO23: =AN23 -> 437923 | AP23: =AO23+2077 -> 440000 | AQ23: =AP23 -> 440000 | AR23: =AQ23 -> 440000 | AS23: =AR23 -> 440000 | AT23: =AS23 -> 440000 | AU23: =AT23 -> 440000 | AV23: =AU23-AT23 -> 0 | AW23: =AU23-AI23 -> 2077
A24: Депозиты и субординированные депозиты в ВЭБ.РФ | B24: Капитализацция процентов по проекту в Усть-Луге | AP24: =24553 -> 24553 | AQ24: =AP24 -> 24553 | AR24: =AQ24 -> 24553 | AS24: =AR24 -> 24553 | AT24: =AS24 -> 24553 | AU24: =AT24 -> 24553 | AV24: =AU24-AT24 -> 0 | AW24: =AU24-AI24 -> 24553
A25: Депозиты и субординированные депозиты в ВЭБ.РФ | B25: Депозит в ВЭБ.РФ в целях финансирования инфраструктурного проекта с ежегодной уплатой процентов по ставке, равной ключевой ставке Банка России (Усть-Луга) | C25: 0 | D25: 0 | E25: 0 | F25: 0 | G25: 0 | H25: 0 | I25: 0 | J25: 0 | K25: 0 | L25: 0 | M25: 0 | N25: 0 | O25: 0 | P25: 0 | Q25: 0 | R25: 0 | S25: 0 | T25: 0 | U25: 0 | V25: 0 | W25: 0 | X25: 0 | Y25: 0 | Z25: 0 | AA25: 0 | AB25: 0 | AC25: 0 | AD25: 0 | AE25: 0 | AF25: 0 | AG25: 0 | AH25: 0 | AI25: 0 | AJ25: 0 | AK25: 133424 | AL25: =AK25+18524 -> 151948 | AM25: =AL25+25452 -> 177400 | AN25: =AM25 -> 177400 | AO25: =AN25 -> 177400 | AP25: =AO25 -> 177400 | AQ25: =AP25 -> 177400 | AR25: =AQ25 -> 177400 | AS25: =AR25 -> 177400 | AT25: =AS25 -> 177400 | AU25: =AT25 -> 177400 | AV25: =AU25-AT25 -> 0 | AW25: =AU25-AI25 -> 177400
A26: Депозиты и субординированные депозиты в ВЭБ.РФ | B26: Субординированный депозит (Программа Фабрика проектного финансирования) | G26: 120000 | L26: 120000 | M26: 120000 | N26: 120000 | O26: 120000 | P26: =O26 -> 120000 | Q26: 120000 | R26: =Q26 -> 120000 | S26: =R26 -> 120000 | T26: =S26 -> 120000 | U26: =T26 -> 120000 | V26: =U26 -> 120000 | W26: =V26 -> 120000 | X26: =W26 -> 120000 | Y26: =X26 -> 120000 | ... AU26: =AT26 -> 120000 | AV26: =AU26-AT26 -> 0 | AW26: =AU26-AI26 -> 0
A27: Долговые обязательства иностранных государств | B27: Долговые обязательства иностранных государств, млн. долл. США | C27: 3000 | D27: 3000 | E27: 3000 | F27: 3000 | G27: 3000 | H27: 3000 | I27: 3000 | J27: 3000 | K27: 3000 | L27: 3000 | M27: 3000 | N27: 3000 | O27: 3000 | P27: 3000 | Q27: 3000 | R27: =Q27 -> 3000 | S27: =R27 -> 3000 | T27: =S27 -> 3000 | U27: =T27 -> 3000 | V27: 3000 | W27: 3000 | X27: =W27 -> 3000 | Y27: =X27 -> 3000 | Z27: 3000 | AA27: 3000 | AB27: 3000 | AC27: 3000 | AD27: =AC27 -> 3000 | AE27: =AD27 -> 3000 | AF27: =AE27 -> 3000 | AG27: =AF27 -> 3000 | AH27: =AG27 -> 3000 | AI27: 3000 | AJ27: =AI27 -> 3000 | AK27: =AJ27 -> 3000 | AL27: =AK27 -> 3000 | AM27: =AL27 -> 3000 | AN27: =AM27 -> 3000 | AO27: =AN27 -> 3000 | AP27: =AO27 -> 3000 | AQ27: =AP27 -> 3000 | ... AU27: =AT27 -> 3000 | AV27: =AU27-AT27 -> 0 | AW27: =AU27-AI27 -> 0
A28: Ценные бумаги российских эмитентов, связанные с реализацией самоокупаемых инфраструктурных проектов | B28: Ценные бумаги российских эмитентов, связанные с реализацией самоокупаемых инфраструктурных проектов, млн. руб. | C28: 314357.4 | D28: 319388.7 | E28: 385146.2 | F28: 583710 | G28: 583710 | H28: 583710 | I28: 595596 | J28: 603639.1 | K28: 619314.4 | L28: 697875.5 | M28: 703010.4 | N28: 862315.2 | O28: 918404.2 | P28: 940395.4 | Q28: =386744.9+140891.8+117073.5+88556.5+4050+178300+57500 -> 973116.7 | R28: 1157407 | S28: =R28 -> 1157407 | T28: 1163373 | U28: 1179302 | V28: 1182890 | W28: 1213962.3 | X28: 1231367.6 | Y28: 1236574.6 | Z28: 1262976 | AA28: 1270394.2 | AB28: 1283924.4 | AC28: 1296899.4 | AD28: 1339327.2 | AE28: 1339073.1 | AF28: 1338488.3 | AG28: 1340916 | AH28: 1340825.6 | AI28: 1347272.4 | AJ28: 1350046.2 | AK28: 1349572.1 | AL28: 1349460.9 | AM28: 1347890.4 | AN28: 1348143.9 | AO28: 1346460 | AP28: 1351077.6 | AQ28: 1350589.5 | AR28: 1347391.2 | AS28: 1344847.3 | AT28: 1347322.5 | AU28: =GETPIVOTDATA("Сумма, млн. руб",infra_invest!$J$2,"Получатель","АО «Атомэнергопром»")+GETPIVOTDATA("Сумма, млн. руб",infra_invest!$J$2,"Получатель","АО «ГТЛК»")+GETPIVOTDATA("Сумма, млн. руб",infra_invest!$J$2,"Получатель","ГК «Российские автомобильные дороги»")+GETPIVOTDATA("Сумма, млн. руб",infra_invest!$J$2,"Получатель","ГК Фонд содействия реформированию жилищно-коммунального хозяйства")+GETPIVOTDATA("Сумма, млн. руб",infra_invest!$J$2,"Получатель","ООО «Авиакапитал-Сервис»")+GETPIVOTDATA("Сумма, млн. руб",infra_invest!$J$2,"Получатель","ООО «Инфраструктурные инвестиции - 4»")+GETPIVOTDATA("Сумма, млн. руб",infra_invest!$J$2,"Получатель","ППК «Фонд развития территорий»")+GETPIVOTDATA("Сумма, млн. руб",infra_invest!$J$2,"Получатель","ОАО «РЖД»") -> 1344250.1 | AV28: =AU28-AT28 -> -3072.4 | AW28: =AU28-AI28 -> -3022.3
A29: Ценные бумаги российских эмитентов, связанные с реализацией самоокупаемых инфраструктурных проектов | B29: Ценные бумаги российских эмитентов, связанные с реализацией самоокупаемых инфраструктурных проектов, млн. долл. США | C29: 2221.4 | D29: 2221.4 | E29: 2221.4 | F29: 2153.4 | G29: 2153.4 | H29: 2082.4 | I29: 2082.4 | J29: 2082.4 | K29: 2082.4 | L29: 2014.4 | M29: 2014.4 | N29: 1943.5 | O29: 1943.5 | P29: 1943.5 | Q29: 1943.5 | R29: 1875.5 | S29: =R29 -> 1875.5 | T29: =S29 -> 1875.5 | U29: =T29 -> 1875.5 | V29: =U29 -> 1875.5 | W29: 1875.4 | X29: =W29 -> 1875.4 | Y29: =X29 -> 1875.4 | Z29: =Y29 -> 1875.4 | AA29: =Z29 -> 1875.4 | AB29: =AA29 -> 1875.4 | AC29: =AB29 -> 1875.4 | AD29: =AC29 -> 1875.4 | AE29: =AD29 -> 1875.4 | ... AU29: =AT29 -> 1875.4 | AV29: =AU29-AT29 -> 0 | AW29: =AU29-AI29 -> 0
A30: Привилегированные акции кредитных организаций | B30: Банк ВТБ, млн. руб | C30: 214037.9 | D30: 214037.9 | E30: 214037.9 | F30: 214037.9 | G30: 214037.9 | H30: 214037.9 | I30: 214037.9 | J30: 214037.9 | K30: 214037.9 | L30: 214037.9 | M30: 214037.9 | N30: 214037.9 | O30: 214037.9 | P30: 214037.9 | Q30: 214037.9 | R30: =Q30 -> 214037.9 | S30: =R30 -> 214037.9 | T30: =S30 -> 214037.9 | U30: =T30 -> 214037.9 | V30: =U30 -> 214037.9 | W30: =V30 -> 214037.9 | X30: =W30 -> 214037.9 | Y30: =X30 -> 214037.9 | ... AD30: =AC30 -> 214037.9 | AE30: 214038 | AF30: =AE30 -> 214038 | AG30: 214038 | AH30: 214038 | AI30: =AH30 -> 214038 | AJ30: =AI30 -> 214038 | AK30: =AJ30 -> 214038 | AL30: =AK30 -> 214038 | AM30: =AL30 -> 214038 | AN30: =AM30 -> 214038 | AO30: =AN30 -> 214038 | AP30: =AO30 -> 214038 | ... AS30: =AR30 -> 214038 | AT30: 0 | AU30: 0 | AV30: =AU30-AT30 -> 0 | AW30: =AU30-AI30 -> -214038
A31: Привилегированные акции кредитных организаций | B31: Россельхозбанк, млн. руб | C31: 25000 | D31: 25000 | E31: 25000 | F31: 25000 | G31: 25000 | H31: 25000 | I31: 25000 | J31: 25000 | K31: 25000 | L31: 25000 | M31: 25000 | N31: 25000 | O31: 25000 | P31: 25000 | Q31: 25000 | R31: =Q31 -> 25000 | S31: =R31 -> 25000 | T31: =S31 -> 25000 | U31: =T31 -> 25000 | V31: =U31 -> 25000 | W31: =V31 -> 25000 | X31: =W31 -> 25000 | Y31: =X31 -> 25000 | ... AD31: =AC31 -> 25000 | AE31: 25000 | AF31: =AE31 -> 25000 | AG31: =AF31 -> 25000 | AH31: =AG31 -> 25000 | AI31: =AH31 -> 25000 | AJ31: =AI31 -> 25000 | AK31: =AJ31 -> 25000 | AL31: =AK31 -> 25000 | AM31: =AL31 -> 25000 | ... AS31: =AR31 -> 25000 | AT31: 25000 | AU31: =AT31 -> 25000 | AV31: =AU31-AT31 -> 0 | AW31: =AU31-AI31 -> 0
A32: Привилегированные акции кредитных организаций | B32: Банк ГПБ, млн. руб | C32: 89954 | D32: 89954 | E32: 89954 | F32: 89954 | G32: 89954 | H32: 89954 | I32: 89954 | J32: 89954 | K32: 89954 | L32: 89954 | M32: 89954 | N32: 89954 | O32: 89954 | P32: 89954 | Q32: 89954 | R32: =Q32 -> 89954 | S32: =R32 -> 89954 | T32: =S32 -> 89954 | U32: =T32 -> 89954 | V32: =U32 -> 89954 | W32: =V32 -> 89954 | X32: 164954 | Y32: =X32 -> 164954 | Z32: =Y32 -> 164954 | AA32: =Z32 -> 164954 | AB32: =AA32 -> 164954 | AC32: =AB32 -> 164954 | AD32: =AC32 -> 164954 | AE32: 164954 | AF32: =AE32 -> 164954 | AG32: =AF32 -> 164954 | AH32: =AG32 -> 164954 | AI32: =AH32 -> 164954 | AJ32: =AI32 -> 164954 | AK32: =AJ32 -> 164954 | AL32: =AK32 -> 164954 | AM32: =AL32+30000 -> 194954 | AN32: =AM32 -> 194954 | AO32: =AN32 -> 194954 | AP32: =AO32 -> 194954 | AQ32: =AP32 -> 194954 | AR32: =AQ32 -> 194954 | AS32: =AR32 -> 194954 | AT32: 194954 | AU32: =AT32 -> 194954 | AV32: =AU32-AT32 -> 0 | AW32: =AU32-AI32 -> 30000
A33: Субординированные депозиты | B33: Субординированные депозиты в Банк ВТБ (ПАО) и Банк ГПБ (АО) в целях финансирования самоокупаемых инфраструктурных проектов, млн. руб. | C33: 138433.9 | D33: 138433.9 | E33: 138433.9 | F33: 138433.9 | G33: 138433.9 | H33: 138433.9 | I33: 0 | J33: 0 | K33: 0 | L33: 0 | M33: 0 | N33: 0 | O33: 0 | P33: 0 | Q33: 0 | R33: 0 | S33: 0 | T33: 0 | U33: 0 | V33: 0 | W33: 0 | X33: 0 | Y33: 0 | Z33: 0 | AA33: 0 | AB33: 0 | AC33: 0 | AD33: 0 | AE33: 0 | AF33: 0 | AG33: =AF33 -> 0 | AH33: 0 | AI33: 0 | AJ33: 0 | AK33: 0 | AL33: 0 | AM33: =AL33 -> 0 | AN33: 0 | AO33: 0 | AP33: 0 | AQ33: 0 | AR33: 0 | AS33: 0 | AT33: 0 | AU33: =AT33 -> 0 | AV33: =AU33-AT33 -> 0 | AW33: =AU33-AI33 -> 0
A34: Субординированные депозиты | B34: Субординированные депозиты в Банке ГПБ (АО) в целях финансирования самоокупаемых инфраструктурных проектов, млн. руб.*** | C34: 0 | D34: 0 | E34: 0 | F34: 0 | G34: 0 | H34: 0 | I34: 38433.9 | J34: 38433.9 | K34: 38433.9 | L34: 38433.9 | M34: 38433.9 | N34: 38433.9 | O34: 38433.9 | P34: 38433.9 | Q34: 38433.9 | R34: =Q34 -> 38433.9 | S34: =R34 -> 38433.9 | T34: =S34 -> 38433.9 | U34: =T34 -> 38433.9 | V34: =U34 -> 38433.9 | W34: =V34 -> 38433.9 | X34: =W34 -> 38433.9 | Y34: =X34 -> 38433.9 | ... AU34: =AT34 -> 38433.9 | AV34: =AU34-AT34 -> 0 | AW34: =AU34-AI34 -> 0
A35: Субординированные депозиты | B35: Субординированный депозит в ПАО Сбербанк в целях финансирования «Москва - Санкт-Петербург» проекта, млн. руб.**** | C35: 0 | D35: 0 | E35: 0 | F35: 0 | G35: 0 | H35: 0 | I35: 0 | J35: 0 | K35: 0 | L35: 0 | M35: 0 | N35: 0 | O35: 0 | P35: 0 | Q35: 0 | R35: 0 | S35: 0 | T35: 0 | U35: 0 | V35: 0 | W35: 0 | X35: 0 | Y35: 0 | Z35: 0 | AA35: 0 | AB35: 0 | AC35: 0 | AD35: 0 | AE35: 0 | AF35: 0 | AG35: 0 | AH35: 0 | AI35: 94200 | AJ35: =AI35 -> 94200 | AK35: =AJ35 -> 94200 | AL35: =AK35 -> 94200 | AM35: =AL35 -> 94200 | AN35: =AM35 -> 94200 | AO35: =AN35 -> 94200 | AP35: =AO35 -> 94200 | AQ35: 94225.8 | AR35: =AQ35 -> 94225.8 | AS35: 94267.5 | AT35: 94267.5 | AU35: =AT35 -> 94267.5 | AV35: =AU35-AT35 -> 0 | AW35: =AU35-AI35 -> 67.5
A36: Субординированные депозиты | B36: Субординированный депозит в Банке ВТБ (ПАО) в целях финансирования «Москва - Санкт-Петербург» проекта, млн. руб.**** | C36: 0 | D36: 0 | E36: 0 | F36: 0 | G36: 0 | H36: 0 | I36: 0 | J36: 0 | K36: 0 | L36: 0 | M36: 0 | N36: 0 | O36: 0 | P36: 0 | Q36: 0 | R36: 0 | S36: 0 | T36: 0 | U36: 0 | V36: 0 | W36: 0 | X36: 0 | Y36: 0 | Z36: 0 | AA36: 0 | AB36: 0 | AC36: 0 | AD36: 0 | AE36: 0 | AF36: 0 | AG36: 0 | AH36: 0 | AI36: 93180 | AJ36: =AI36 -> 93180 | AK36: =AJ36 -> 93180 | AL36: =AK36 -> 93180 | AM36: =AL36 -> 93180 | AN36: =AM36 -> 93180 | AO36: =AN36 -> 93180 | AP36: =AO36 -> 93180 | AQ36: 93205.5 | AR36: =AQ36 -> 93205.5 | AS36: =AR36+41.3 -> 93246.8 | AT36: =AS36 -> 93246.8 | AU36: =AT36 -> 93246.8 | AV36: =AU36-AT36 -> 0 | AW36: =AU36-AI36 -> 66.8
A37: Субординированные депозиты | B37: Субординированный депозит в Банке ГПБ (АО) в целях финансирования «Москва - Санкт-Петербург» проекта, млн. руб.**** | C37: 0 | D37: 0 | E37: 0 | F37: 0 | G37: 0 | H37: 0 | I37: 0 | J37: 0 | K37: 0 | L37: 0 | M37: 0 | N37: 0 | O37: 0 | P37: 0 | Q37: 0 | R37: 0 | S37: 0 | T37: 0 | U37: 0 | V37: 0 | W37: 0 | X37: 0 | Y37: 0 | Z37: 0 | AA37: 0 | AB37: 0 | AC37: 0 | AD37: 0 | AE37: 0 | AF37: 0 | AG37: 0 | AH37: 0 | AI37: 83055 | AJ37: =AI37 -> 83055 | AK37: =AJ37 -> 83055 | AL37: =AK37 -> 83055 | AM37: =AL37 -> 83055 | AN37: =AM37 -> 83055 | AO37: =AN37 -> 83055 | AP37: =AO37 -> 83055 | AQ37: =AP37 -> 83055 | ... AU37: =AT37 -> 83055 | AV37: =AU37-AT37 -> 0 | AW37: =AU37-AI37 -> 0
A38: Субординированные депозиты | B38: Субординированный депозит в Банке ГПБ (АО) в целях финансирования инфраструктурного проекта с ежегодной уплатой процентов по ставке, равной ключевой ставке Банка России (Усть-Луга) | AP38: 82600 | AQ38: =AP38 -> 82600 | AR38: =AQ38 -> 82600 | AS38: =AR38+59.6 -> 82659.6 | AT38: =AS38 -> 82659.6 | AU38: =AT38 -> 82659.6 | AV38: =AU38-AT38 -> 0 | AW38: =AU38-AI38 -> 82659.6
A39: Субординированные депозиты | B39: Субординированный депозит в ПАО «Совкомбанк» в целях финансирования «Москва - Санкт-Петербург» проекта, млн. руб.**** | C39: 0 | D39: 0 | E39: 0 | F39: 0 | G39: 0 | H39: 0 | I39: 0 | J39: 0 | K39: 0 | L39: 0 | M39: 0 | N39: 0 | O39: 0 | P39: 0 | Q39: 0 | R39: 0 | S39: 0 | T39: 0 | U39: 0 | V39: 0 | W39: 0 | X39: 0 | Y39: 0 | Z39: 0 | AA39: 0 | AB39: 0 | AC39: 0 | AD39: 0 | AE39: 0 | AF39: 0 | AG39: 0 | AH39: 0 | AI39: 29565 | AJ39: =AI39 -> 29565 | AK39: =AJ39 -> 29565 | AL39: =AK39 -> 29565 | AM39: =AL39 -> 29565 | AN39: =AM39 -> 29565 | AO39: =AN39 -> 29565 | AP39: =AO39 -> 29565 | AQ39: =29573.1 -> 29573.1 | AR39: =AQ39 -> 29573.1 | AS39: 29586.2 | AT39: =AS39 -> 29586.2 | AU39: =AT39 -> 29586.2 | AV39: =AU39-AT39 -> 0 | AW39: =AU39-AI39 -> 21.2
A40: Субординированные депозиты | B40: Cубординированный депозит в Банке ВТБ (ПАО) в целях финансирования инфраструктурного проекта с ежегодной уплатой процентов по ставке, равной ключевой ставке Банка России | C40: 0 | D40: 0 | E40: 0 | F40: 0 | G40: 0 | H40: 0 | I40: 0 | J40: 0 | K40: 0 | L40: 0 | M40: 0 | N40: 0 | O40: 0 | P40: 0 | Q40: 0 | R40: 0 | S40: 0 | T40: 0 | U40: 0 | V40: 0 | W40: 0 | X40: 0 | Y40: 0 | Z40: 0 | AA40: 0 | AB40: 0 | AC40: 0 | AD40: 0 | AE40: 0 | AF40: 0 | AG40: 0 | AH40: 0 | AI40: 0 | AJ40: 0 | AK40: 200000 | AL40: =AK40 -> 200000 | AM40: =AL40 -> 200000 | AN40: =AM40 -> 200000 | AO40: =AN40 -> 200000 | AP40: =AO40 -> 200000 | AQ40: =AP40 -> 200000 | AR40: =AQ40 -> 200000 | AS40: =AR40 -> 200000 | ... AU40: =AT40 -> 200000 | AV40: =AU40-AT40 -> 0 | AW40: =AU40-AI40 -> 200000
A41: Обыкновенные акции | B41: ПАО Сбербанк, млн. руб (11293474001 * 189,44 руб) | C41: 1231892.1 | D41: 1432125.4 | E41: 1534896.1 | F41: 1590911.7 | G41: 1758281 | H41: 1920003.5 | I41: 2420417.3 | J41: 2708739.7 | K41: 2756172.3 | L41: 2705012.9 | M41: 2931447 | N41: 2997062.1 | O41: 2944773.3 | P41: 3028345.1 | Q41: 3110787.4 | R41: 3067646.3 | S41: 3113497.8 | T41: 3303115.3 | U41: 3373360.7 | V41: 3483246.2 | W41: 3553491.6 | X41: 3698838.6 | Y41: 3271719.4 | Z41: 2895985.5 | AA41: 3057256.3 | AB41: 2708852.7 | AC41: 2632508.8 | AD41: 3124000.8 | AE41: 3190971.1 | AF41: 3466757.7 | AG41: 3457722.9 | AH41: 3461111 | AI41: 3483133.3 | AJ41: 3569867.1 | AK41: 3437507.6 | AL41: 3505381.4 | AM41: 3247551.4 | AN41: 3316554.5 | AO41: 3413791.3 | AP41: 3387816.3 | AQ41: 3454899.6 | AR41: 3553265.7 | AS41: 3548070.7 | AT41: 3612895.3 | AU41: 3622833.5 | AV41: =AU41-AT41 -> 9938.2 | AW41: =AU41-AI41 -> 139700.2
A42: Обыкновенные акции | B42: ПАО Аэрофлот, млн. Руб (1531234889 акций * 34,29 руб, 833333333 акций * 60 руб) | C42: 53439.2 | D42: 60627.5 | E42: 58793.2 | F42: 58073.8 | G42: 65876.9 | H42: 66822.7 | I42: 74507.5 | J42: 94511.8 | K42: 94157.1 | L42: 100730.6 | M42: 107256.8 | N42: 104111.9 | O42: 97869.5 | P42: 92785.7 | Q42: 86046.6 | R42: 82901.8 | S42: 92076.3 | T42: 90823.1 | U42: 105719.8 | V42: 121964.4 | W42: 130264.1 | X42: 148471.2 | Y42: 128206.9 | Z42: 112884.5 | AA42: 130145.8 | AB42: 127426.6 | AC42: 126433.5 | AD42: 139533.2 | AE42: 152585.6 | AF42: 171738.6 | AG42: 162233 | AH42: 166442 | AI42: 160696.1 | AJ42: 157172.8 | AK42: 134520.3 | AL42: 147076.1 | AM42: 128892.6 | AN42: 119670.8 | AO42: 133219.8 | AP42: 136719.3 | AQ42: 135915.4 | AR42: 132061.1 | AS42: 112458.9 | AT42: 111820.4 | AU42: 114303.2 | AV42: =AU42-AT42 -> 2482.8 | AW42: =AU42-AI42 -> -46392.9
A43: Обыкновенные акции | B43: АО ДОМ.РФ, млн.руб | C43: 50000 | D43: 50000 | E43: 50000 | F43: 50000 | G43: 50000 | H43: 50000 | I43: 50000 | J43: 50000 | K43: 50000 | L43: 137000 | M43: 137000 | N43: 137000 | O43: 137000 | P43: 137000 | Q43: 137000 | R43: =Q43 -> 137000 | S43: 137000 | T43: =S43 -> 137000 | U43: =T43 -> 137000 | V43: =U43 -> 137000 | W43: 137000 | X43: =W43 -> 137000 | Y43: =X43 -> 137000 | Z43: =Y43 -> 137000 | AA43: =Z43 -> 137000 | AB43: =AA43 -> 137000 | AC43: =AB43 -> 137000 | AD43: =AC43 -> 137000 | AE43: =AD43 -> 137000 | ... AO43: =AN43 -> 137000 | AP43: 181368.4 | AQ43: 207192.9 | AR43: 225824.9 | AS43: 214297.4 | AT43: 218299.7 | AU43: 235659.6 | AV43: =AU43-AT43 -> 17359.9 | AW43: =AU43-AI43 -> 98659.6
A44: Обыкновенные акции | B44: АО ГТЛК, млн. руб | C44: 58334 | D44: 58334 | E44: 58334 | F44: 58334 | G44: 58334 | H44: 58334 | I44: 58334 | J44: 58334 | K44: 58334 | L44: 58334 | M44: 58334 | N44: 58334 | O44: 58334 | P44: 58334 | Q44: 58334 | R44: 58334 | S44: 58334 | T44: =S44 -> 58334 | U44: =T44 -> 58334 | V44: =U44 -> 58334 | W44: 58334 | X44: =W44 -> 58334 | Y44: =X44 -> 58334 | Z44: =Y44 -> 58334 | AA44: =Z44 -> 58334 | AB44: =AA44 -> 58334 | AC44: =AB44 -> 58334 | AD44: =AC44 -> 58334 | AE44: =AD44 -> 58334 | AF44: =AE44 -> 58334 | AG44: 58334 | AH44: =AG44 -> 58334 | AI44: =AH44 -> 58334 | AJ44: =AI44 -> 58334 | AK44: =AJ44 -> 58334 | AL44: =AK44 -> 58334 | AM44: =AL44 -> 58334 | AN44: =AM44 -> 58334 | AO44: =AN44 -> 58334 | AP44: 58334 | AQ44: =AP44 -> 58334 | AR44: 58334 | AS44: =AR44 -> 58334 | AT44: 58334 | AU44: =AT44 -> 58334 | AV44: =AU44-AT44 -> 0 | AW44: =AU44-AI44 -> 0
A45: Обыкновенные акции | B45: Банк ВТБ (ПАО), млн.руб* | C45: 0 | D45: 0 | E45: 0 | F45: 0 | G45: 0 | H45: 0 | I45: 105853.1 | J45: 130289.7 | K45: 130084.9 | L45: 127216.9 | M45: 150482.9 | N45: 168598.2 | O45: 151214.5 | P45: 147205.2 | Q45: 138806 | R45: 133713.8 | S45: =143693.3 -> 143693.3 | T45: 136845.2 | U45: 133040.7 | V45: 137137.8 | W45: 116856.9 | X45: 125021.9 | Y45: 114989.8 | Z45: 109206.9 | AA45: 105730.2 | AB45: 88416.7 | AC45: 81568.6 | AD45: 93052.4 | AE45: 99549.3 | AF45: 105777 | AG45: 95674.6 | AH45: 113339.2 | AI45: 110670.2 | AJ45: 124542 | AK45: 90992.1 | AL45: 88042.1 | AM45: 79847.8 | AN45: 80046.8 | AO45: 84612.2 | AP45: 84682.5 | AQ45: =90945.3 -> 90945.3 | AR45: 101633 | AS45: 99227.4 | AT45: 343728.9 | AU45: 296413.3 | AV45: =AU45-AT45 -> -47315.6 | AW45: =AU45-AI45 -> 185743.1
A46: Привилегированные акции | B46: ОАО РЖД, млн. руб | C46: 250000 | D46: 250000 | E46: 250000 | F46: 467000 | G46: 467000 | H46: 467000 | I46: 467000 | J46: 467000 | K46: 467000 | L46: 467000 | M46: 467000 | N46: 467000 | O46: 467000 | P46: 467000 | Q46: 467000 | R46: =Q46 -> 467000 | S46: =R46 -> 467000 | T46: =S46 -> 467000 | U46: =T46 -> 467000 | V46: =U46 -> 467000 | W46: =V46 -> 467000 | X46: =W46 -> 467000 | Y46: =X46 -> 467000 | ... AU46: =AT46 -> 467000 | AV46: =AU46-AT46 -> 0 | AW46: =AU46-AI46 -> 0
A47: Облигации | B47: АО Авиакомпания Сибирь, млн. руб | C47: 11851.9 | D47: 11851.9 | E47: 11851.9 | F47: 11851.9 | G47: 11851.9 | H47: 11851.9 | I47: 11851.9 | J47: 11851.9 | K47: 11851.9 | L47: 11851.9 | M47: 0 | N47: 0 | O47: 0 | P47: 0 | Q47: 0 | R47: 0 | S47: 0 | T47: 0 | U47: 0 | V47: 0 | W47: 0 | X47: 0 | Y47: 0 | Z47: 0 | AA47: 0 | AB47: 0 | AC47: 0 | AD47: 0 | AE47: 0 | AF47: 0 | AG47: 0 | AH47: 0 | AI47: 0 | AJ47: 0 | AK47: 0 | AL47: 0 | AM47: 0 | AN47: 0 | AO47: 0 | AP47: 0 | AQ47: 0 | AR47: 0 | AS47: 0 | AT47: =AS47 -> 0 | AU47: =AT47 -> 0 | AV47: =AU47-AT47 -> 0 | AW47: =AU47-AI47 -> 0
A48: Облигации | B48: ОАО АК Уральские авилинии, млн. руб | C48: 2298.9 | D48: 2298.9 | E48: 2298.9 | F48: 2298.9 | G48: 2298.9 | H48: 2298.9 | I48: 2298.9 | J48: 2298.9 | K48: 2298.9 | L48: 2298.9 | M48: 2298.9 | N48: 2298.9 | O48: 0 | P48: 0 | Q48: 0 | R48: 0 | S48: 0 | T48: 0 | U48: 0 | V48: 0 | W48: 0 | X48: 0 | Y48: 0 | Z48: 0 | AA48: 0 | AB48: 0 | AC48: 0 | AD48: 0 | AE48: 0 | AF48: 0 | AG48: 0 | AH48: 0 | AI48: 0 | AJ48: 0 | AK48: 0 | AL48: 0 | AM48: 0 | AN48: 0 | AO48: 0 | AP48: 0 | AQ48: 0 | AR48: 0 | AS48: 0 | AT48: =AS48 -> 0 | AU48: =AT48 -> 0 | AV48: =AU48-AT48 -> 0 | AW48: =AU48-AI48 -> 0
A49: Облигации | B49: ООО НЛК-Финанс, млн. руб | C49: 0 | D49: 0 | E49: 0 | F49: 0 | G49: 0 | H49: 0 | I49: 0 | J49: 34948.1 | K49: 34948.1 | L49: 34948.1 | M49: 34423.9 | N49: 97014.5 | O49: 167543.5 | P49: 185719.7 | Q49: 190195.1 | R49: 296818.8 | S49: 296014 | T49: 294994 | U49: 292320.8 | V49: 291516.1 | W49: 290496 | X49: 287822.8 | Y49: 287018.1 | Z49: 285998 | AA49: 282911.8 | AB49: 282107.1 | AC49: 281087 | AD49: =278420.3 -> 278420.3 | AE49: 277615.6 | AF49: 276595.5 | AG49: 273928.8 | AH49: 273124.1 | AI49: 272104 | AJ49: 269437.3 | AK49: 268632.6 | AL49: 267612.5 | AM49: 264945.8 | AN49: 264141.1 | AO49: 263121 | AP49: 260454.3 | AQ49: 259649.6 | AR49: 258629.5 | AS49: 255962.8 | AT49: 255158.1 | AU49: 254138 | AV49: =AU49-AT49 -> -1020.1 | AW49: =AU49-AI49 -> -17966
A50: Облигации | B50: ООО ВК, млн. руб | C50: 0 | D50: 0 | E50: 0 | F50: 0 | G50: 0 | H50: 0 | I50: 0 | J50: 60000 | K50: 60000 | L50: 60000 | M50: 60000 | N50: 60000 | O50: 60000 | P50: 60000 | Q50: 60000 | R50: 60000 | S50: =R50 -> 60000 | T50: =S50 -> 60000 | U50: =T50 -> 60000 | V50: =U50 -> 60000 | W50: =V50 -> 60000 | X50: =W50 -> 60000 | Y50: =X50 -> 60000 | Z50: =Y50 -> 60000 | AA50: 60000 | AB50: =AA50 -> 60000 | AC50: =AB50 -> 60000 | AD50: =AC50 -> 60000 | AE50: 60000 | AF50: =AE50 -> 60000 | AG50: =AF50 -> 60000 | AH50: =AG50 -> 60000 | AI50: =AH50 -> 60000 | AJ50: =AI50 -> 60000 | AK50: =AJ50 -> 60000 | AL50: =AK50 -> 60000 | AM50: =AL50 -> 60000 | ... AU50: =AT50 -> 60000 | AV50: =AU50-AT50 -> 0 | AW50: =AU50-AI50 -> 0
A51: Облигации | B51: Иные российские эмитенты, млн. руб. | C51: 0 | D51: 0 | E51: 0 | F51: 0 | G51: 0 | H51: 0 | I51: 0 | J51: 0 | K51: 0 | L51: 0 | M51: 0 | N51: 0 | O51: 0 | P51: 0 | Q51: 0 | R51: 11000 | S51: =R51 -> 11000 | T51: =S51 -> 11000 | U51: =T51 -> 11000 | V51: =U51 -> 11000 | W51: =V51 -> 11000 | X51: 16000 | Y51: =X51 -> 16000 | Z51: =Y51+12500 -> 28500 | AA51: =Z51 -> 28500 | AB51: =AA51 -> 28500 | AC51: =AB51+21200 -> 49700 | AD51: =AC51 -> 49700 | AE51: =AD51 -> 49700 | AF51: =AE51 -> 49700 | AG51: =AF51 -> 49700 | AH51: =AG51 -> 49700 | AI51: =AH51+8700 -> 58400 | AJ51: =AI51 -> 58400 | AK51: =AJ51 -> 58400 | AL51: =AK51 -> 58400 | AM51: =AL51 -> 58400 | AN51: =AM51 -> 58400 | AO51: =AN51 -> 58400 | AP51: =AO51+5300 -> 63700 | AQ51: =AP51 -> 63700 | AR51: =AQ51 -> 63700 | AS51: =AR51 -> 63700 | AT51: =AS51 -> 63700 | AU51: =AT51 -> 63700 | AV51: =AU51-AT51 -> 0 | AW51: =AU51-AI51 -> 5300
A52: Облигации | B52: Иные российские эмитенты, млн. юаней | C52: 0 | D52: 0 | E52: 0 | F52: 0 | G52: 0 | H52: 0 | I52: 0 | J52: 0 | K52: 0 | L52: 0 | M52: 0 | N52: 0 | O52: 0 | P52: 0 | Q52: 0 | R52: 0 | S52: 0 | T52: 0 | U52: 0 | V52: 0 | W52: 0 | X52: 0 | Y52: 3000 | Z52: =Y52+2750 -> 5750 | AA52: =Z52+2000 -> 7750 | AB52: =AA52+1250 -> 9000 | AC52: =AB52+1000 -> 10000 | AD52: =AC52 -> 10000 | AE52: =AD52 -> 10000 | AF52: =AE52 -> 10000 | AG52: =AF52 -> 10000 | AH52: =AG52 -> 10000 | AI52: =AH52 -> 10000 | AJ52: =AI52 -> 10000 | AK52: =AJ52 -> 10000 | ... AU52: =AT52 -> 10000 | AV52: =AU52-AT52 -> 0 | AW52: =AU52-AI52 -> 0
A53: Облигации | B53: ГК Ростех, млн. руб. | C53: 0 | D53: 0 | E53: 0 | F53: 0 | G53: 0 | H53: 0 | I53: 0 | J53: 0 | K53: 0 | L53: 0 | M53: 0 | N53: 0 | O53: 0 | P53: 0 | Q53: 0 | R53: 17952.4 | S53: =R53 -> 17952.4 | T53: =S53 -> 17952.4 | U53: 153989.7 | V53: =U53 -> 153989.7 | W53: =V53 -> 153989.7 | X53: =247324.7 -> 247324.7 | Y53: =X53 -> 247324.7 | Z53: =Y53 -> 247324.7 | AA53: =Z53 -> 247324.7 | AB53: =AA53 -> 247324.7 | AC53: =AB53 -> 247324.7 | AD53: =AC53+111093.5 -> 358418.2 | AE53: =AD53 -> 358418.2 | AF53: =AE53 -> 358418.2 | AG53: =AF53 -> 358418.2 | AH53: =AG53 -> 358418.2 | AI53: =AH53 -> 358418.2 | AJ53: =AI53+11791.7 -> 370209.9 | AK53: =AJ53 -> 370209.9 | AL53: =AK53 -> 370209.9 | AM53: =AL53 -> 370209.9 | AN53: =AM53 -> 370209.9 | AO53: =AN53 -> 370209.9 | AP53: =AO53+41825-122.7 -> 411912.2 | AQ53: =AP53 -> 411912.2 | AR53: =AQ53 -> 411912.2 | AS53: =AR53 -> 411912.2 | AT53: =AS53 -> 411912.2 | AU53: =AT53 -> 411912.2 | AV53: =AU53-AT53 -> 0 | AW53: =AU53-AI53 -> 53494
AV54: =AU54-AT54 -> 0 | AW54: =AU54-AI54 -> 0
A55: Объем активов Фонда | B55: Общий объем ФНБ, млн. руб | C55: 10792186 | D55: 11374082 | E55: 11389508 | F55: 10434581 | G55: 10807595 | H55: 11106404 | I55: 11906061 | J55: 12475588 | K55: 12353146 | L55: 12670270 | M55: 13313450 | N55: 13703598 | O55: 13648338 | P55: 13541232 | Q55: 13432972 | R55: 11965075 | S55: 11922371 | T55: 12258661 | U55: 12534406 | V55: 12750839 | W55: 12703814 | X55: 12601672 | Y55: 12277511 | Z55: 12165767 | AA55: 12787133 | AB55: 12726199 | AC55: 13096719 | AD55: 11879973 | AE55: 11965802 | AF55: 11880606 | AG55: 11750726 | AH55: 11791774 | AI55: 11696344 | AJ55: 13090579 | AK55: 13080455 | AL55: 13142340 | AM55: 13162797 | AN55: 13201461 | AO55: 13259021 | AP55: 13415159 | AQ55: 13639254 | AR55: 13548757 | AS55: 13413795 | AT55: 13213193 | AU55: 12955276 | AV55: =AU55-AT55 -> -257916.5 | AW55: =AU55-AI55 -> 1258932.2
A56: Объем активов Фонда | B56: Общий объем ФНБ, млн. долл США | C56: 187974.6 | D56: 184841.3 | E56: 186486.4 | F56: 148350.2 | G56: 155297.8 | H56: 147236.7 | I56: 154451.1 | J56: 154958.3 | K56: 153099.2 | L56: 145578.2 | M56: 146336.5 | N56: 142852.5 | O56: 140105.5 | P56: 145224.4 | Q56: 151129.1 | R56: 133407.3 | S56: 133526.1 | T56: 133436 | U56: 135703.7 | V56: 138929.7 | W56: 141488.5 | X56: 146961.7 | Y56: 142216 | Z56: 133415.9 | AA56: 137922.3 | AB56: 131126.3 | AC56: 121557.5 | AD56: 116837.2 | AE56: 122092.3 | AF56: 135473.8 | AG56: 140422.4 | AH56: 144575.1 | AI56: 148776.1 | AJ56: 166825.9 | AK56: 159840 | AL56: 163601.1 | AM56: 158841.3 | AN56: 163985.8 | AO56: 169491.1 | AP56: 171490.8 | AQ56: 180097.3 | AR56: 175334.9 | AS56: 165000.5 | AT56: 176456.8 | AU56: 182411.1 | AV56: =AU56-AT56 -> 5954.3 | AW56: =AU56-AI56 -> 33635
A57: Доля фонда в ВВП | B57: Доля ВВП | C57: 0.081 | D57: 0.085 | E57: 0.085 | F57: 0.078 | G57: 0.072 | H57: 0.074 | I57: 0.079 | J57: 0.083 | K57: 0.082 | L57: 0.084 | M57: 0.089 | N57: 0.091 | O57: 0.091 | P57: 0.09 | Q57: 0.09 | R57: 0.08 | S57: 0.066 | T57: 0.068 | U57: 0.07 | V57: 0.071 | W57: 0.071 | X57: 0.07 | Y57: 0.064 | Z57: 0.064 | AA57: 0.067 | AB57: 0.066 | AC57: 0.068 | AD57: 0.062 | AE57: 0.056 | AF57: 0.055 | AG57: 0.055 | AH57: 0.055 | AI57: 0.055 | AJ57: 0.059 | AK57: 0.059 | AL57: 0.059 | AM57: 0.059 | AN57: 0.06 | AO57: 0.061 | AP57: 0.062 | AQ57: 0.058 | AR57: 0.058 | AS57: 0.057 | AT57: 0.056 | AU57: 0.055 | AV57: =AU57-AT57 -> -0.001 | AW57: =AU57-AI57 -> 0
AV58: =AU58-AT58 -> 0 | AW58: =AU58-AI58 -> 0
A59: Объем ликвидных активов Фонда | B59: Средства на банковских счетах в Банке России, млн. руб | C59: 7524361.3 | D59: 7872548.3 | E59: 7601763 | F59: 6132655.2 | G59: 6334590.6 | H59: 6446231 | I59: 6712063.4 | J59: 6828671.4 | K59: 6643004.4 | L59: 6811125 | M59: 7183391.5 | N59: 7251634.9 | O59: 7140176.1 | P59: 6938308.8 | Q59: 6746505.1 | R59: 5011778 | S59: 4907126.4 | T59: 5044614.2 | U59: 5087766.7 | V59: 5172247.3 | W59: 5046039 | X59: 4603329.1 | Y59: 4665093 | Z59: 4854458.2 | AA59: 5255172.1 | AB59: 5447193.4 | AC59: 5792014.8 | AD59: 3809866.8 | AE59: 3751160.1 | AF59: 3393844.7 | AG59: 3268903.8 | AH59: 3296830.6 | AI59: 2843025 | AJ59: 4127953.1 | AK59: 3952913.1 | AL59: 3927556.8 | AM59: 4164859 | AN59: 4157548 | AO59: 4114666.1 | AP59: 4084984.2 | AQ59: 4226461.5 | AR59: 4004966.9 | AS59: 3889150.8 | AT59: 3625531.4 | AU59: 3412351.9 | AV59: =AU59-AT59 -> -213179.5 | AW59: =AU59-AI59 -> 569326.9
A60: Объем ликвидных активов Фонда | B60: Средства на банковских счетах в Банке России, млн. долл США | C60: 131056.8 | D60: 127937.6 | E60: 124467.7 | F60: 87189 | G60: 91023.8 | H60: 85457.2 | I60: 87072.1 | J60: 84818.4 | K60: 82330.3 | L60: 78258.1 | M60: 78957.2 | N60: 75594.3 | O60: 73296.7 | P60: 74410.6 | Q60: 75905.3 | R60: 55880 | S60: 54958 | T60: 54910.8 | U60: 55082.7 | V60: 56355.4 | W60: 56200.2 | X60: 53684.4 | Y60: 54037.9 | Z60: 53236.4 | AA60: 56682.4 | AB60: 56126 | AC60: 53758.7 | AD60: 37469.3 | AE60: 38274.7 | AF60: 38699.8 | AG60: 39063.7 | AH60: 40421.4 | AI60: 36162.9 | AJ60: 52606.5 | AK60: 48303.6 | AL60: 48891.8 | AM60: 50259.2 | AN60: 51644.2 | AO60: 52598.1 | AP60: 52219.8 | AQ60: 55807.6 | AR60: 51828.4 | AS60: 47839.7 | AT60: 48417.5 | AU60: 48046.1 | AV60: =AU60-AT60 -> -371.4 | AW60: =AU60-AI60 -> 11883.2
A61: Доля ликвидных средств в ВВП | B61: Доля ВВП | C61: 0.056 | D61: 0.059 | E61: 0.057 | F61: 0.046 | G61: 0.042 | H61: 0.043 | I61: 0.045 | J61: 0.046 | K61: 0.044 | L61: 0.045 | M61: 0.048 | N61: 0.048 | O61: 0.048 | P61: 0.046 | Q61: 0.045 | R61: 0.033 | S61: 0.027 | T61: 0.028 | U61: 0.028 | V61: 0.029 | W61: 0.028 | X61: 0.026 | Y61: 0.024 | Z61: 0.025 | AA61: 0.025 | AB61: 0.028 | AC61: 0.03 | AD61: 0.02 | AE61: 0.017 | AF61: 0.016 | AG61: 0.015 | AH61: 0.015 | AI61: 0.013 | AJ61: 0.019 | AK61: 0.018 | AL61: =AK61 -> 0.018 | AM61: 0.019 | AN61: 0.019 | AO61: 0.019 | AP61: =AO61 -> 0.019 | AQ61: 0.018 | AR61: 0.017 | AS61: 0.017 | AT61: 0.015 | AU61: =AT61 -> 0.015 | AV61: =AU61-AT61 -> 0 | AW61: =AU61-AI61 -> 0.002
A62: Доля ликвидных средств в общем объеме Фонда | B62: Доля ликвидных средств в общем объеме Фонда в долл. США эквиваленте | C62: =C60/C56 -> 0.69720484 | D62: =D60/D56 -> 0.69214835 | E62: =E60/E56 -> 0.6674358 | F62: =F60/F56 -> 0.58772418 | G62: =G60/G56 -> 0.58612421 | H62: =H60/H56 -> 0.58040692 | I62: =I60/I56 -> 0.56375189 | J62: =J60/J56 -> 0.54736274 | ... AU62: =AU60/AU56 -> 0.26339461 | AV62: =AU62-AT62 -> -0.010992665 | AW62: =AU62-AI62 -> 0.020325324
A65: * За счет субординированного депозита приобретение облигаций ГК "Российские автомобильные дороги" для реализации проекта «Центральная кольцевая автомобильная дорога (Московская область)», млн: 400 + 400 + 450 + 800 + 680 + 1350 + 500 + 2000 + 4000 + 2000
A66: **В июне 2020 г. срок возврата депозита, размещенного в 2012 г. продлен до 8 июня 2028 г. при одновременном снижении процентной ставки с 6,25% до 4,75% годовых.
A67: *** облигации ГК «Автодор» в целях финансирования инфраструктурного проекта «Центральная кольцевая автомобильная дорога (Московская область)» 2017 год
A68: **** инфраструктурного проекта «Финансирование, создание и эксплуатация инфраструктуры высокоскоростного железнодорожного транспорта общего пользования от станции Крюково (Алабушево) до станции Санкт-Петербург-Главный, приобретение и эксплуатация высокоскоростного железнодорожного подвижного состава, предназначенного для перевозки пассажиров и (или) багажа на созданной инфраструктуре по маршруту «Москва - Санкт-Петербург» на срок до декабря 2049 г. с ежеквартальной уплатой процентов по ставке 1 % годовых (в течение 10 лет с даты выдачи первого транша проценты капитализируются) – в части средств, фактически направленных на финансирование указанного инфраструктурного проекта, и по ставке, равной процентной ставке, установленной Банком России при проведении депозитных операций по фиксированным процентным ставкам, – в части средств, временно не направленных на финансирование указанного инфраструктурного проекта и размещаемых в Банке России и (или) системно значимых кредитных организациях в рамках операций по управлению ликвидностью

Sheet rnwf_structure
A1: Data | B1: 01.10.2022 | C1: 01.11.2022 | D1: 01.12.2022 | E1: 01.01.2023 | F1: 01.02.2023 | G1: 01.03.2023 | H1: 01.04.2023 | I1: 01.05.2023 | J1: 01.06.2023 | K1: 01.07.2023 | L1: 01.08.2023 | M1: 01.09.2023 | N1: 01.10.2023 | O1: 01.11.2023 | P1: 01.12.2023 | Q1: 01.01.2024 | R1: 01.02.2024 | S1: 01.03.2024 | T1: 01.04.2024 | U1: 01.05.2024 | V1: 01.06.2024 | W1: 01.07.2024 | X1: 01.08.2024 | Y1: 01.09.2024 | Z1: 01.10.2024 | AA1: 01.11.2024 | AB1: 01.12.2024 | AC1: 01.01.2025 | AD1: 01.02.2025 | AE1: 01.03.2025 | AF1: 01.04.2025 | AG1: 01.05.2025 | AH1: 01.06.2025 | AI1: 01.07.2025 | AJ1: 01.08.2025 | AK1: 01.09.2025 | AL1: 01.10.2025 | AM1: 01.11.2025 | AN1: 01.12.2025 | AO1: 01.01.2026 | AP1: 01.02.2026 | AQ1: 01.03.2026 | AR1: 01.04.2026 | AS1: 01.05.2026 | AT1: 01.06.2026
A2: Volume of the National Wealth Fund, RUB mln | B2: =Main_!C55 -> 10792186 | C2: =Main_!D55 -> 11374082 | D2: =Main_!E55 -> 11389508 | E2: =Main_!F55 -> 10434581 | F2: =Main_!G55 -> 10807595 | G2: =Main_!H55 -> 11106404 | H2: =Main_!I55 -> 11906061 | I2: =Main_!J55 -> 12475588 | ... AT2: =Main_!AU55 -> 12955276
A3: Volume of the National Wealth Fund, USD mln | B3: =Main_!C56 -> 187974.6 | C3: =Main_!D56 -> 184841.3 | D3: =Main_!E56 -> 186486.4 | E3: =Main_!F56 -> 148350.2 | F3: =Main_!G56 -> 155297.8 | G3: =Main_!H56 -> 147236.7 | H3: =Main_!I56 -> 154451.1 | I3: =Main_!J56 -> 154958.3 | ... AT3: =Main_!AU56 -> 182411.1
A4: Balance on Federal Treasury accounts with the Bank of the Russia, EUR mln | B4: =Main_!C2 -> 49188.8 | C4: =Main_!D2 -> 45733.5 | D4: =Main_!E2 -> 41891.7 | E4: =Main_!F2 -> 10464.5 | F4: =Main_!G2 -> 10464.5 | G4: =Main_!H2 -> 10464.5 | H4: =Main_!I2 -> 10398.8 | I4: =Main_!J2 -> 9233.6 | ... AJ4: =Main_!AK2 -> 0 | AK4: 0 | AL4: 0 | AM4: 0 | AN4: 0 | AO4: 0 | AP4: 0 | AQ4: 0 | AR4: 0 | AS4: 0 | AT4: 1
A5: Balance on Federal Treasury accounts with the Bank of the Russia, CNY mln | B5: =Main_!C5 -> 309720.1 | C5: =Main_!D5 -> 309720.1 | D5: =Main_!E5 -> 309720.1 | E5: =Main_!F5 -> 309720.1 | F5: =Main_!G5 -> 307445.9 | G5: =Main_!H5 -> 300067.9 | H5: =Main_!I5 -> 292588.8 | I5: =Main_!J5 -> 288330.1 | ... AT5: =Main_!AU5 -> 185546.9
A6: Balance on Federal Treasury accounts with the Bank of the Russia, GOLD kg | B6: =Main_!C6 -> 554910.5 | C6: =Main_!D6 -> 554910.5 | D6: =Main_!E6 -> 554910.5 | E6: =Main_!F6 -> 554910.5 | F6: =Main_!G6 -> 551277.5 | G6: =Main_!H6 -> 539245.1 | H6: =Main_!I6 -> 527382.3 | I6: =Main_!J6 -> 520974 | ... AT6: =Main_!AU6 -> 145180.1
A7: Balance on Federal Treasury accounts with the Bank of the Russia, RUB mln | B7: =Main_!C7 -> 264.3 | C7: =Main_!D7 -> 526.7 | D7: =Main_!E7 -> 242.7 | E7: =Main_!F7 -> 274.8 | F7: =Main_!G7 -> 530.1 | G7: =Main_!H7 -> 6124 | H7: =Main_!I7 -> 140.7 | I7: =Main_!J7 -> 232.8 | ... AT7: =Main_!AU7 -> 1534
A8: Deposits and subordinated debt with VEB_RF, RUB mln | B8: 528449 | C8: 528186 | D8: 650116 | E8: 649841 | F8: 649586 | G8: 649346 | H8: 648927 | I8: 648694 | J8: 648466 | K8: =SUM(Main_!L8:L26) -> 653020 | L8: =SUM(Main_!M8:M26) -> 655170.8 | M8: =SUM(Main_!N8:N26) -> 656580 | N8: =SUM(Main_!O8:O26) -> 657029.3 | O8: =SUM(Main_!P8:P26) -> 657764.8 | P8: =SUM(Main_!Q8:Q26) -> 658364.9 | Q8: =SUM(Main_!R8:R26) -> 658828.3 | R8: =SUM(Main_!S8:S26) -> 658595.7 | ... AT8: =SUM(Main_!AU8:AU26) -> 1321371.6
A9: Debt obligations of foreign countries, USD mln | B9: =Main_!C27 -> 3000 | C9: =Main_!D27 -> 3000 | D9: =Main_!E27 -> 3000 | E9: =Main_!F27 -> 3000 | F9: =Main_!G27 -> 3000 | G9: =Main_!H27 -> 3000 | H9: =Main_!I27 -> 3000 | I9: =Main_!J27 -> 3000 | ... AT9: =Main_!AU27 -> 3000
A10: Securities of Russian issuers related to the implementation of self-sustaining infrastructure projects, RUB mln | B10: =Main_!C28 -> 314357.4 | C10: =Main_!D28 -> 319388.7 | D10: =Main_!E28 -> 385146.2 | E10: =Main_!F28 -> 583710 | F10: =Main_!G28 -> 583710 | G10: =Main_!H28 -> 583710 | H10: =Main_!I28 -> 595596 | I10: =Main_!J28 -> 603639.1 | ... AT10: =Main_!AU28 -> 1344250.1
A11: Securities of Russian issuers related to the implementation of self-sustaining infrastructure projects, USD mln | B11: =Main_!C29 -> 2221.4 | C11: =Main_!D29 -> 2221.4 | D11: =Main_!E29 -> 2221.4 | E11: =Main_!F29 -> 2153.4 | F11: =Main_!G29 -> 2153.4 | G11: =Main_!H29 -> 2082.4 | H11: =Main_!I29 -> 2082.4 | I11: =Main_!J29 -> 2082.4 | ... AT11: =Main_!AU29 -> 1875.4
A12: Preferred shares of credit organizations, RUB mln | B12: =SUM(Main_!C30:C32) -> 328991.9 | C12: =SUM(Main_!D30:D32) -> 328991.9 | D12: =SUM(Main_!E30:E32) -> 328991.9 | E12: =SUM(Main_!F30:F32) -> 328991.9 | F12: =SUM(Main_!G30:G32) -> 328991.9 | G12: =SUM(Main_!H30:H32) -> 328991.9 | H12: =SUM(Main_!I30:I32) -> 328991.9 | I12: =SUM(Main_!J30:J32) -> 328991.9 | ... AT12: =SUM(Main_!AU30:AU32) -> 219954
A13: Subordinated debt of the banks, RUB mln | B13: =Main_!C34 -> 0 | C13: =Main_!D34 -> 0 | D13: =Main_!E34 -> 0 | E13: =Main_!F34 -> 0 | F13: =Main_!G34 -> 0 | G13: =Main_!H34 -> 0 | H13: =Main_!I34 -> 38433.9 | I13: =Main_!J34 -> 38433.9 | ... AG13: =Main_!AH34 -> 38433.9 | AH13: =SUM(Main_!AI34:AI39) -> 338433.9 | AI13: =SUM(Main_!AJ34:AJ39) -> 338433.9 | AJ13: =SUM(Main_!AK33:AK40) -> 538433.9 | AK13: =SUM(Main_!AL33:AL40) -> 538433.9 | AL13: =SUM(Main_!AM33:AM40) -> 538433.9 | AM13: =SUM(Main_!AN33:AN40) -> 538433.9 | AN13: =SUM(Main_!AO33:AO40) -> 538433.9 | AO13: =SUM(Main_!AP33:AP40) -> 621033.9 | AP13: =SUM(Main_!AQ33:AQ40) -> 621093.3 | AQ13: =SUM(Main_!AR33:AR40) -> 621093.3 | ... AT13: =SUM(Main_!AU33:AU40) -> 621249
A14: Common stocks, RUB mln | B14: =SUM(Main_!C41:C45) -> 1393665.3 | C14: =SUM(Main_!D41:D45) -> 1601086.9 | D14: =SUM(Main_!E41:E45) -> 1702023.3 | E14: =SUM(Main_!F41:F45) -> 1757319.5 | F14: =SUM(Main_!G41:G45) -> 1932491.9 | G14: =SUM(Main_!H41:H45) -> 2095160.2 | H14: =SUM(Main_!I41:I45) -> 2709111.9 | I14: =SUM(Main_!J41:J45) -> 3041875.2 | ... AT14: =SUM(Main_!AU41:AU45) -> 4327543.6
A15: Preferred shares, RUB mln | B15: =Main_!C46 -> 250000 | C15: =Main_!D46 -> 250000 | D15: =Main_!E46 -> 250000 | E15: =Main_!F46 -> 467000 | F15: =Main_!G46 -> 467000 | G15: =Main_!H46 -> 467000 | H15: =Main_!I46 -> 467000 | I15: =Main_!J46 -> 467000 | ... AT15: =Main_!AU46 -> 467000
A16: Bonds, RUB mln | B16: =SUM(Main_!C47:C50) -> 14150.8 | C16: =SUM(Main_!D47:D50) -> 14150.8 | D16: =SUM(Main_!E47:E50) -> 14150.8 | E16: =SUM(Main_!F47:F50) -> 14150.8 | F16: =SUM(Main_!G47:G50) -> 14150.8 | G16: =SUM(Main_!H47:H50) -> 14150.8 | H16: =SUM(Main_!I47:I50) -> 14150.8 | I16: =SUM(Main_!J47:J50) -> 109098.9 | ... P16: =SUM(Main_!Q47:Q50) -> 250195.1 | Q16: =SUM(Main_!R47:R53) -> 385771.2 | R16: =SUM(Main_!S47:S53) -> 384966.4 | S16: =SUM(Main_!T47:T53) -> 383946.4 | T16: =SUM(Main_!U47:U53) -> 517310.5 | U16: =SUM(Main_!V47:V53) -> 516505.8 | V16: =SUM(Main_!W47:W53) -> 515485.7 | W16: =SUM(Main_!X47:X53) -> 611147.5 | X16: =SUM(Main_!Y47:Y51)+Main_!Y53 -> 610342.8 | Y16: =SUM(Main_!Z47:Z51)+Main_!Z53 -> 621822.7 | Z16: =SUM(Main_!AA47:AA51)+Main_!AA53 -> 618736.5 | AA16: =SUM(Main_!AB47:AB51)+Main_!AB53 -> 617931.8 | AB16: =SUM(Main_!AC47:AC51)+Main_!AC53 -> 638111.7 | AC16: =SUM(Main_!AD47:AD51)+Main_!AD53 -> 746538.5 | AD16: =SUM(Main_!AE47:AE51)+Main_!AE53 -> 745733.8 | AE16: =SUM(Main_!AF47:AF51)+Main_!AF53 -> 744713.7 | ... AT16: =SUM(Main_!AU47:AU51)+Main_!AU53 -> 789750.2
A17: Bonds, CNY mln | B17: 0 | C17: 0 | D17: 0 | E17: 0 | F17: 0 | G17: 0 | H17: 0 | I17: 0 | J17: 0 | K17: 0 | L17: 0 | M17: 0 | N17: 0 | O17: 0 | P17: 0 | Q17: 0 | R17: 0 | S17: 0 | T17: 0 | U17: 0 | V17: 0 | W17: 0 | X17: =Main_!Y52 -> 3000 | Y17: =Main_!Z52 -> 5750 | Z17: =Main_!AA52 -> 7750 | AA17: =Main_!AB52 -> 9000 | AB17: =Main_!AC52 -> 10000 | AC17: =Main_!AD52 -> 10000 | AD17: =Main_!AE52 -> 10000 | AE17: =Main_!AF52 -> 10000 | ... AT17: =Main_!AU52 -> 10000
A18: Volume of liquid assets of the Fund, RUB mln | B18: =Main_!C59 -> 7524361.3 | C18: =Main_!D59 -> 7872548.3 | D18: =Main_!E59 -> 7601763 | E18: =Main_!F59 -> 6132655.2 | F18: =Main_!G59 -> 6334590.6 | G18: =Main_!H59 -> 6446231 | H18: =Main_!I59 -> 6712063.4 | I18: =Main_!J59 -> 6828671.4 | ... AT18: =Main_!AU59 -> 3412351.9
A19: Volume of liquid assets of the Fund, USD mln | B19: =Main_!C60 -> 131056.8 | C19: =Main_!D60 -> 127937.6 | D19: =Main_!E60 -> 124467.7 | E19: =Main_!F60 -> 87189 | F19: =Main_!G60 -> 91023.8 | G19: =Main_!H60 -> 85457.2 | H19: =Main_!I60 -> 87072.1 | I19: =Main_!J60 -> 84818.4 | ... AT19: =Main_!AU60 -> 48046.1
A20: Share of liquid assets in the total Fund in USD equivalent | B20: =Main_!C62 -> 0.69720484 | C20: =Main_!D62 -> 0.69214835 | D20: =Main_!E62 -> 0.6674358 | E20: =Main_!F62 -> 0.58772418 | F20: =Main_!G62 -> 0.58612421 | G20: =Main_!H62 -> 0.58040692 | H20: =Main_!I62 -> 0.56375189 | I20: =Main_!J62 -> 0.54736274 | ... AT20: =Main_!AU62 -> 0.26339461

Sheet structure
A1: =rnwf_structure!A1 -> Data | B1: 01.10.2022 | C1: 01.11.2022 | D1: 01.12.2022 | E1: 01.01.2023 | F1: 01.02.2023 | G1: 01.03.2023 | H1: 01.04.2023 | I1: 01.05.2023 | J1: 01.06.2023 | K1: 01.07.2023 | L1: 01.08.2023 | M1: 01.09.2023 | N1: 01.10.2023 | O1: 01.11.2023 | P1: 01.12.2023 | Q1: 01.01.2024 | R1: 01.02.2024 | S1: 01.03.2024 | T1: 01.04.2024 | U1: 01.05.2024 | V1: 01.06.2024 | W1: 01.07.2024 | X1: 01.08.2024 | Y1: 01.09.2024 | Z1: 01.10.2024 | AA1: 01.11.2024 | AB1: 01.12.2024 | AC1: 01.01.2025 | AD1: 01.02.2025 | AE1: 01.03.2025 | AF1: 01.04.2025 | AG1: 01.05.2025 | AH1: 01.06.2025 | AI1: 01.07.2025 | AJ1: 01.08.2025 | AK1: 01.09.2025 | AL1: 01.10.2025 | AM1: 01.11.2025 | AN1: 01.12.2025 | AO1: 01.01.2026 | AP1: 01.02.2026 | AQ1: 01.03.2026 | AR1: 01.04.2026 | AS1: 01.05.2026 | AT1: 01.06.2026
A2: CBR exchange rate for USD | B2: 57 | C2: 61 | D2: 61 | E2: 70 | F2: 69 | G2: 75 | H2: 77 | I2: 80 | J2: 81 | K2: 87 | L2: 91 | M2: 96 | N2: 97 | O2: 93 | P2: 89 | Q2: 90 | R2: 89 | S2: 92 | T2: 92 | U2: 92 | V2: 90 | W2: 86 | X2: 86 | Y2: 91 | Z2: 93 | AA2: 97 | AB2: 108 | AC2: 102 | AD2: 98 | AE2: 88 | AF2: 84 | AG2: 82 | AH2: 79 | AI2: 78 | AJ2: 82 | AK2: 80 | AL2: 83 | AM2: 80 | AN2: 78 | AO2: 78 | AP2: 76 | AQ2: 77 | AR2: 81 | AS2: 75 | AT2: 71
A3: CBR exchange rate for CNY | B3: 8 | C3: 8 | D3: 9 | E3: 10 | F3: 10 | G3: 11 | H3: 11 | I3: 12 | J3: 11 | K3: 12 | L3: 13 | M3: 13 | N3: 13 | O3: 13 | P3: 12 | Q3: 13 | R3: 12 | S3: 13 | T3: 13 | U3: 12 | V3: 12 | W3: 12 | X3: 12 | Y3: 12 | Z3: 13 | AA3: 13 | AB3: 15 | AC3: 13 | AD3: 13 | AE3: 12 | AF3: 11 | AG3: 11 | AH3: 11 | AI3: 11 | AJ3: 11 | AK3: 11 | AL3: 12 | AM3: 11 | AN3: 11 | AO3: 11 | AP3: 11 | AQ3: 11 | AR3: 12 | AS3: 11 | AT3: 10
A4: Volume of the National Wealth Fund, RUB mln | B4: =rnwf_structure!B2 -> 10792186 | C4: =rnwf_structure!C2 -> 11374082 | D4: =rnwf_structure!D2 -> 11389508 | E4: =rnwf_structure!E2 -> 10434581 | F4: =rnwf_structure!F2 -> 10807595 | G4: =rnwf_structure!G2 -> 11106404 | H4: =rnwf_structure!H2 -> 11906061 | I4: =rnwf_structure!I2 -> 12475588 | ... AT4: =rnwf_structure!AT2 -> 12955276
A5: Deposits and subordinated debt with VEB_RF | B5: =rnwf_structure!B8 -> 528449 | C5: =rnwf_structure!C8 -> 528186 | D5: =rnwf_structure!D8 -> 650116 | E5: =rnwf_structure!E8 -> 649841 | F5: =rnwf_structure!F8 -> 649586 | G5: =rnwf_structure!G8 -> 649346 | H5: =rnwf_structure!H8 -> 648927 | I5: =rnwf_structure!I8 -> 648694 | ... AT5: =rnwf_structure!AT8 -> 1321371.6
A6: Debt obligations of foreign countries | B6: =rnwf_structure!B9*B2 -> 171000 | C6: =rnwf_structure!C9*C2 -> 183000 | D6: =rnwf_structure!D9*D2 -> 183000 | E6: =rnwf_structure!E9*E2 -> 210000 | F6: =rnwf_structure!F9*F2 -> 207000 | G6: =rnwf_structure!G9*G2 -> 225000 | H6: =rnwf_structure!H9*H2 -> 231000 | I6: =rnwf_structure!I9*I2 -> 240000 | ... AT6: =rnwf_structure!AT9*AT2 -> 213000
A7: Securities related to the implementation of infrastructure projects | B7: =(rnwf_structure!B10+(rnwf_structure!B11*B2)) -> 440977.2 | C7: =(rnwf_structure!C10+(rnwf_structure!C11*C2)) -> 454894.1 | D7: =(rnwf_structure!D10+(rnwf_structure!D11*D2)) -> 520651.6 | E7: =(rnwf_structure!E10+(rnwf_structure!E11*E2)) -> 734448 | F7: =(rnwf_structure!F10+(rnwf_structure!F11*F2)) -> 732294.6 | G7: =(rnwf_structure!G10+(rnwf_structure!G11*G2)) -> 739890 | H7: =(rnwf_structure!H10+(rnwf_structure!H11*H2)) -> 755940.8 | I7: =(rnwf_structure!I10+(rnwf_structure!I11*I2)) -> 770231.1 | ... AT7: =(rnwf_structure!AT10+(rnwf_structure!AT11*AT2)) -> 1477403.5
A8: Preferred shares and subordinated debt of credit organizations | B8: =(rnwf_structure!B12+rnwf_structure!B13) -> 328991.9 | C8: =(rnwf_structure!C12+rnwf_structure!C13) -> 328991.9 | D8: =(rnwf_structure!D12+rnwf_structure!D13) -> 328991.9 | E8: =(rnwf_structure!E12+rnwf_structure!E13) -> 328991.9 | F8: =(rnwf_structure!F12+rnwf_structure!F13) -> 328991.9 | G8: =(rnwf_structure!G12+rnwf_structure!G13) -> 328991.9 | H8: =(rnwf_structure!H12+rnwf_structure!H13) -> 367425.8 | I8: =(rnwf_structure!I12+rnwf_structure!I13) -> 367425.8 | ... AT8: =(rnwf_structure!AT12+rnwf_structure!AT13) -> 841203
A9: Common stocks | B9: =rnwf_structure!B14 -> 1393665.3 | C9: =rnwf_structure!C14 -> 1601086.9 | D9: =rnwf_structure!D14 -> 1702023.3 | E9: =rnwf_structure!E14 -> 1757319.5 | F9: =rnwf_structure!F14 -> 1932491.9 | G9: =rnwf_structure!G14 -> 2095160.2 | H9: =rnwf_structure!H14 -> 2709111.9 | I9: =rnwf_structure!I14 -> 3041875.2 | ... AT9: =rnwf_structure!AT14 -> 4327543.6
A10: Preferred shares | B10: =rnwf_structure!B15 -> 250000 | C10: =rnwf_structure!C15 -> 250000 | D10: =rnwf_structure!D15 -> 250000 | E10: =rnwf_structure!E15 -> 467000 | F10: =rnwf_structure!F15 -> 467000 | G10: =rnwf_structure!G15 -> 467000 | H10: =rnwf_structure!H15 -> 467000 | I10: =rnwf_structure!I15 -> 467000 | ... AT10: =rnwf_structure!AT15 -> 467000
A11: Bonds | B11: =rnwf_structure!B16 -> 14150.8 | C11: =rnwf_structure!C16 -> 14150.8 | D11: =rnwf_structure!D16 -> 14150.8 | E11: =rnwf_structure!E16 -> 14150.8 | F11: =rnwf_structure!F16 -> 14150.8 | G11: =rnwf_structure!G16 -> 14150.8 | H11: =rnwf_structure!H16 -> 14150.8 | I11: =rnwf_structure!I16 -> 109098.9 | ... W11: =rnwf_structure!W16 -> 611147.5 | X11: =rnwf_structure!X16+rnwf_structure!X17*X3 -> 646342.8 | Y11: =rnwf_structure!Y16+rnwf_structure!Y17*Y3 -> 690822.7 | Z11: =rnwf_structure!Z16+rnwf_structure!Z17*Z3 -> 719486.5 | AA11: =rnwf_structure!AA16+rnwf_structure!AA17*AA3 -> 734931.8 | AB11: =rnwf_structure!AB16+rnwf_structure!AB17*AB3 -> 788111.7 | AC11: =rnwf_structure!AC16+rnwf_structure!AC17*AC3 -> 876538.5 | AD11: =rnwf_structure!AD16+rnwf_structure!AD17*AD3 -> 875733.8 | AE11: =rnwf_structure!AE16+rnwf_structure!AE17*AE3 -> 864713.7 | ... AT11: =rnwf_structure!AT16+rnwf_structure!AT17*AT3 -> 889750.2
A12: Liquid assets of the Fund | B12: =rnwf_structure!B18 -> 7524361.3 | C12: =rnwf_structure!C18 -> 7872548.3 | D12: =rnwf_structure!D18 -> 7601763 | E12: =rnwf_structure!E18 -> 6132655.2 | F12: =rnwf_structure!F18 -> 6334590.6 | G12: =rnwf_structure!G18 -> 6446231 | H12: =rnwf_structure!H18 -> 6712063.4 | I12: =rnwf_structure!I18 -> 6828671.4 | ... AT12: =rnwf_structure!AT18 -> 3412351.9

Sheet recepients
A1: Entity | B1: RUB, mln
A2: Sberbank | B2: =Main_!AU41+Main_!AU35 -> 3717101
A3: VEB.RF | B3: =SUM(Main_!AU8:AU26) -> 1321371.6
A4: RZD | B4: =Main_!AU46+GETPIVOTDATA("Сумма, млн. руб",infra_invest!$N$2,"Получатель","ОАО «РЖД»") -> 722141.3
A5: VTB | B5: =Main_!AU30+Main_!AU36+Main_!AU40+Main_!AU45 -> 589660.1
A6: Avtodor | B6: =GETPIVOTDATA("Сумма, млн. руб",infra_invest!$N$2,"Получатель","ГК «Российские автомобильные дороги»") -> 520430.3
A7: Rosteh | B7: =Main_!AU53 -> 411912.2
A8: Gazprombank | B8: =Main_!AU32+Main_!AU34+Main_!AU37+Main_!AU38 -> 399102.5
A9: NLK-Finance | B9: =Main_!AU49 -> 254138
A10: GTLK | B10: =GETPIVOTDATA("Сумма, млн. руб",infra_invest!$N$2,"Получатель","АО «ГТЛК»")+Main_!AU44 -> 239826.9
A11: DOM.RF | B11: =Main_!AU43 -> 235659.6
A12: Ukraine | B12: =structure!AT6 -> 213000
A13: Avia Capital Services | B13: =GETPIVOTDATA("Сумма, млн. руб",infra_invest!$N$2,"Получатель","ООО «Авиакапитал-Сервис»") -> 175784.7
A14: Territory Development Fund | B14: =GETPIVOTDATA("Сумма, млн. руб",infra_invest!$N$2,"Получатель","ППК «Фонд развития территорий»")+GETPIVOTDATA("Сумма, млн. руб",infra_invest!$N$2,"Получатель","ГК Фонд содействия реформированию жилищно-коммунального хозяйства") -> 149850.9
A15: Yamal LNG | B15: =Main_!AU29*structure!AT2 -> 133153.4
A16: Aeroflot | B16: =Main_!AU42 -> 114303.2
A17: Other RUS issuers | B17: =rnwf_structure!AT17*structure!AT3 -> 100000
A18: Mayak FSUE | B18: =Main_!AU51 -> 63700
A19: Vkontakte (VK) | B19: =Main_!AU50 -> 60000
A20: Atomenergoprom | B20: =GETPIVOTDATA("Сумма, млн. руб",infra_invest!$N$2,"Получатель","АО «Атомэнергопром»") -> 57500
A21: Sovkombank | B21: =Main_!AU39 -> 29586.2
A22: RSHB | B22: =Main_!AU31 -> 25000
A23: II-4 | B23: =GETPIVOTDATA("Сумма, млн. руб",infra_invest!$N$2,"Получатель","ООО «Инфраструктурные инвестиции - 4»") -> 4050

Sheet income_rub
A1: Type | B1: Issuer | F1: 01.01.2010 | G1: 01.02.2010 | H1: 01.03.2010 | I1: 01.04.2010 | J1: 01.05.2010 | K1: 01.06.2010 | L1: 01.07.2010 | M1: 01.08.2010 | N1: 01.09.2010 | O1: 01.10.2010 | P1: 01.11.2010 | Q1: 01.12.2010 | R1: 01.01.2011 | S1: 01.02.2011 | T1: 01.03.2011 | U1: 01.04.2011 | V1: 01.05.2011 | W1: 01.06.2011 | X1: 01.07.2011 | Y1: 01.08.2011 | Z1: 01.09.2011 | AA1: 01.10.2011 | AB1: 01.11.2011 | AC1: 01.12.2011 | AD1: 01.01.2012 | AE1: 01.02.2012 | AF1: 01.03.2012 | AG1: 01.04.2012 | AH1: 01.05.2012 | AI1: 01.06.2012 | AJ1: 01.07.2012 | AK1: 01.08.2012 | AL1: 01.09.2012 | AM1: 01.10.2012 | AN1: 01.11.2012 | AO1: 01.12.2012 | AP1: 01.01.2013 | AQ1: 01.02.2013 | AR1: 01.03.2013 | AS1: 01.04.2013 | AT1: 01.05.2013 | AU1: 01.06.2013 | AV1: 01.07.2013 | AW1: 01.08.2013 | AX1: 01.09.2013 | AY1: 01.10.2013 | AZ1: 01.11.2013 | BA1: 01.12.2013 | BB1: 01.01.2014 | BC1: 01.02.2014 | BD1: 01.03.2014 | BE1: 01.04.2014 | BF1: 01.05.2014 | BG1: 01.06.2014 | BH1: 01.07.2014 | BI1: 01.08.2014 | BJ1: 01.09.2014 | BK1: 01.10.2014 | BL1: 01.11.2014 | BM1: 01.12.2014 | BN1: 01.01.2015 | BO1: 01.02.2015 | BP1: 01.03.2015 | BQ1: 01.04.2015 | BR1: 01.05.2015 | BS1: 01.06.2015 | BT1: 01.07.2015 | BU1: 01.08.2015 | BV1: 01.09.2015 | BW1: 01.10.2015 | BX1: 01.11.2015 | BY1: 01.12.2015 | BZ1: 01.01.2016 | CA1: 01.02.2016 | CB1: 01.03.2016 | CC1: 01.04.2016 | CD1: 01.05.2016 | CE1: 01.06.2016 | CF1: 01.07.2016 | CG1: 01.08.2016 | CH1: 01.09.2016 | CI1: 01.10.2016 | CJ1: 01.11.2016 | CK1: 01.12.2016 | CL1: 01.01.2017 | CM1: 01.02.2017 | CN1: 01.03.2017 | CO1: 01.04.2017 | CP1: 01.05.2017 | CQ1: 01.06.2017 | CR1: 01.07.2017 | CS1: 01.08.2017 | CT1: 01.09.2017 | CU1: 01.10.2017 | CV1: 01.11.2017 | CW1: 01.12.2017 | CX1: 01.01.2018 | CY1: 01.02.2018 | CZ1: 01.03.2018 | DA1: 01.04.2018 | DB1: 01.05.2018 | DC1: 01.06.2018 | DD1: 01.07.2018 | DE1: 01.08.2018 | DF1: 01.09.2018 | DG1: 01.10.2018 | DH1: 01.11.2018 | DI1: 01.12.2018 | DJ1: 01.01.2019 | DK1: 01.02.2019 | DL1: 01.03.2019 | DM1: 01.04.2019 | DN1: 01.05.2019 | DO1: 01.06.2019 | DP1: 01.07.2019 | DQ1: 01.08.2019 | DR1: 01.09.2019 | DS1: 01.10.2019 | DT1: 01.11.2019 | DU1: 01.12.2019 | DV1: 01.01.2020 | DW1: 01.02.2020 | DX1: 01.03.2020 | DY1: 01.04.2020 | DZ1: 01.05.2020 | EA1: 01.06.2020 | EB1: 01.07.2020 | EC1: 01.08.2020 | ED1: 01.09.2020 | EE1: 01.10.2020 | EF1: 01.11.2020 | EG1: 01.12.2020 | EH1: 01.01.2021 | EI1: 01.02.2021 | EJ1: 01.03.2021 | EK1: 01.04.2021 | EL1: 01.05.2021 | EM1: 01.06.2021 | EN1: 01.07.2021 | EO1: 01.08.2021 | EP1: 01.09.2021 | EQ1: 01.10.2021 | ER1: 01.11.2021 | ES1: 01.12.2021 | ET1: 01.01.2022 | EU1: 01.02.2022 | EV1: 01.03.2022 | EW1: 01.04.2022 | EX1: 01.05.2022 | EY1: 01.06.2022 | EZ1: 01.07.2022 | FA1: 01.08.2022 | FB1: 01.09.2022 | FC1: 01.10.2022 | FD1: 01.11.2022 | FE1: 01.12.2022 | FF1: 01.01.2023 | FG1: 01.02.2023 | FH1: 01.03.2023 | FI1: 01.04.2023 | FJ1: 01.05.2023 | FK1: 01.06.2023 | FL1: 01.07.2023 | FM1: 01.08.2023 | FN1: 01.09.2023 | FO1: 01.10.2023 | FP1: 01.11.2023 | FQ1: 01.12.2023 | FR1: 01.01.2024 | FS1: 01.02.2024 | FT1: 01.03.2024 | FU1: 01.04.2024 | FV1: 01.05.2024 | FW1: 01.06.2024 | FX1: 01.07.2024 | FY1: 01.08.2024 | FZ1: 01.09.2024 | GA1: 01.10.2024 | GB1: 01.11.2024 | GC1: 01.12.2024 | GD1: 01.01.2025 | GE1: 01.02.2025 | GF1: 01.03.2025 | GG1: 01.04.2025 | GH1: 01.05.2025 | GI1: 01.06.2025 | GJ1: 01.07.2025 | GK1: 01.08.2025 | GL1: 01.09.2025 | GM1: 01.10.2025 | GN1: 01.11.2025 | GO1: 01.12.2025 | GP1: 01.01.2026 | GQ1: 01.02.2026 | GR1: 01.03.2026 | GS1: 01.04.2026 | GT1: 01.05.2026 | GU1: 01.06.2026
A2: Common stocks | B2: Sberbank | EF2: 211188 | EM2: 211188 | FL2: 282336.9 | FZ2: 376072.7 | GL2: 393464.6
A3: Preffered stocks | B3: Banks | BU3: 2850 | CG3: 2490 | CS3: 2400 | CT3: 18.9 | DD3: 11804.2 | DF3: 57.4 | DQ3: 5228.7 | DU3: 3781.5 | EF3: 8520.7 | EG3: 6.2 | EO3: 5989 | EP3: 61.7 | FN3: 120.2 | FZ3: 218.4
A4: Preffered stocks | B4: VTB | CQ4: 11130 | GL4: 56805.7
A5: Common stocks | B5: VTB | GL5: 29944.4
A6: Preffered stocks | B6: Gazprombank | GK6: 623 | GL6: 0
A7: Common stocks | B7: DOM.RF | FE7: 6202.5 | FN7: 9108.7 | FZ7: 9073.3 | GL7: 14336.1
A8: Preffered stocks | B8: RZD | FN8: 6535 | FZ8: 6535 | GL8: 6535
A9: Securities | B9: Securities related to the implementation of infrastructure projects | BT9: 190 | BV9: 860 | BW9: 1540 | BZ9: 320 | CC9: 1560 | CF9: 2970 | CG9: 5 | CH9: 180 | CI9: 1520 | CJ9: 220 | CL9: 2910 | CM9: 240 | CO9: 1490 | CR9: 2760 | CS9: 150 | CT9: 5 | CU9: 1670 | CX9: 3260 | CY9: 320 | DA9: 1530.7 | DD9: 3549.9 | DE9: 398.8 | DG9: 2038.5 | DH9: 88.2 | DI9: 1807.5 | DJ9: 2018.8 | DK9: 382 | DM9: 1979.9 | DO9: 1764.7 | DP9: 1964.5 | DQ9: 461.4 | DR9: 7 | DT9: 146.9 | DU9: 1626.6 | DV9: 1972.6 | DW9: 277.4 | DY9: 1995.9 | EA9: 1804.2 | EB9: 2069.8 | EC9: 144.8 | ED9: 752.3 | EE9: 2013.3 | EF9: 2667.1 | EG9: 2178.7 | EH9: 1590.4 | EI9: 504.5 | EK9: 1473.8 | EM9: 2121.1 | EN9: 1496.2 | EP9: 5425.4 | EQ9: 353.2 | ES9: 1566.6 | ET9: 2339 | EV9: 2277.2 | EW9: 1778.6 | EZ9: 1319.3 | FA9: 819.5 | FB9: 5940.3 | FD9: 529.9 | FF9: 2593 | FG9: 266.6 | FH9: 1722.6 | FJ9: 246 | FL9: 2077.2 | FM9: 1000.6 | FN9: 6506.9 | FO9: 1123.4 | FP9: 509.3 | FR9: 3018.7 | FS9: 1741.5 | FT9: 13810.5 | FU9: 590 | FV9: 765.1 | FW9: 42.7 | FX9: 406.8 | FY9: 2424.6 | FZ9: 4743.8 | GA9: 729.9 | GB9: 916.6 | GC9: 162.7 | GD9: 829 | GE9: 1836.8 | GF9: 488.4 | GG9: 1148.7 | GH9: 1020.6 | GI9: 659.9 | GJ9: 2330.5 | GK9: 2098.4 | GL9: 5692.2 | GM9: 2575 | GN9: 1228.6 | GO9: 7152.3 | GP9: 7578.9 | GQ9: 2170.6 | GR9: 2025 | GS9: 8341.1 | GT9: 1085.3 | GU9: 1839.1
A10: Common stocks | B10: GTLK | FY10: 40.6 | GK10: 700.8 | GL10: 0
A11: Common stocks | B11: Aeroflot | GM11: 12461.3
A12: Subordinated deposits | B12: Gazprombank | CD12: 1810 | CP12: 1610 | CT12: 422.2 | EX12: 1281.9 | FB12: 985.7 | FJ12: 2040.2 | FN12: 1568.7 | FV12: 2811.5 | FZ12: 2161.8 | GH12: 1829.4 | GJ12: 1463.1 | GL12: 1406.7 | GM12: 3679.5 | GN12: 112.3 | GO12: 5 | GP12: 3063.5 | GS12: 2484.7 | GT12: 2295.8 | GU12: 504.6
A13: Subordinated deposits | B13: Sberbank | GJ13: 1659.5 | GM13: 4173.2 | GN13: 127.4 | GO13: 5.7 | GP13: 3140.9 | GS13: 2818.1 | GT13: 11.4 | GU13: 572.3
A14: Subordinated deposits | B14: VTB | BQ14: 3580 | BX14: 5970 | CC14: 5710 | CJ14: 6190 | CO14: 5960 | DB14: 3304.1 | DH14: 2339.6 | DN14: 2377.5 | DT14: 2932.6 | DY14: 2666.4 | EF14: 2006.7 | EK14: 1671.8 | ER14: 2343 | EW14: 2744.4 | FD14: 3930 | FI14: 6087.9 | GJ14: 1641.5 | GM14: 4128 | GN14: 126 | GO14: 5.6 | GP14: 3106.9 | GS14: 2787.6 | GT14: 11.3 | GU14: 566.1
A15: Subordinated deposits | B15: Sovkombank | GJ15: 520.8 | GM15: 1309.8 | GN15: 40 | GO15: 1.8 | GP15: 985.8 | GR15: 85.5 | GS15: 799 | GT15: 142.2 | GU15: 41
A16: Deposits | B16: VTB | BU16: 670 | BZ16: 1050 | CG16: 1030 | CM16: 1050 | CS16: 1030 | CV16: 3610 | CY16: 1050 | DE16: 1031.5 | DK16: 1099.8
A17: Deposits | B17: VEB.RF | F17: 13270 | P17: 7780 | Q17: 380 | R17: 1070 | S17: 7140 | V17: 7030 | W17: 330 | Y17: 8000 | AB17: 7190 | AE17: 7440 | AH17: 7660 | AI17: 370 | AJ17: 1200 | AK17: 7420 | AN17: 7280 | AP17: 9290 | AQ17: 6870 | AT17: 6740 | AV17: 1560 | AW17: 6820 | AZ17: 6890 | BB17: 1570 | BC17: 6890 | BF17: 6740 | BI17: 6820 | BK17: 18790 | BL17: 3590 | BN17: 2280 | BO17: 2400 | BR17: 2340 | BT17: 1560 | BU17: 2370 | BW17: 210 | BX17: 2400 | BZ17: 1570 | CA17: 240 | CD17: 2360 | CF17: 1560 | CG17: 2360 | CJ17: 2390 | CL17: 1840 | CM17: 2110 | CP17: 2340 | CR17: 1560 | CS17: 2370 | CV17: 2400 | CW17: 76.4 | CX17: 2540 | CY17: 2290 | CZ17: 46.5 | DA17: 30.9 | DB17: 2254.3 | DC17: 54.5 | DD17: 1593 | DE17: 2265.4 | DF17: 32.9 | DG17: 12822 | DH17: 2302.1 | DI17: 47 | DJ17: 3113.2 | DK17: 2296.1 | DL17: 47.7 | DM17: 65.7 | DN17: 2288.7 | DO17: 81.8 | DP17: 1668.8 | DQ17: 2278.9 | DR17: 99.3 | DS17: 10186.5 | DT17: 2325.4 | DU17: 112 | DV17: 3536.5 | DW17: 2036.5 | DX17: 114.7 | DY17: 82.2 | DZ17: 2001.5 | EA17: 511.3 | EB17: 1686.8 | EC17: 1548.2 | ED17: 126 | EE17: 10219.1 | EF17: 2042.8 | EG17: 126.1 | EH17: 3668.5 | EI17: 1219.5 | EJ17: 118.5 | EK17: 162 | EL17: 1155.8 | EM17: 170.5 | EN17: 1360.7 | EO17: 1226.2 | EP17: 175.5 | EQ17: 10257.4 | ER17: 1237.5 | ES17: 175.1 | ET17: 2863.8 | EU17: 1235.3 | EV17: 167.9 | EW17: 241.7 | EX17: 1535.1 | EY17: 256.5 | EZ17: 1450.9 | FA17: 1659.8 | FB17: 263.7 | FC17: 10349.5 | FD17: 1674.5 | FE17: 262.8 | FF17: 2843.9 | FG17: 2538.6 | FH17: 263.5 | FI17: 326.2 | FJ17: 3905.3 | FK17: 345.6 | FL17: 1545.2 | FM17: 2769.5 | FN17: 377.4 | FO17: 10478.8 | FP17: 3920.6 | FQ17: 395.8 | FR17: 2851.9 | FS17: 5226.5 | FT17: 395.8 | FU17: 263.9 | FV17: 5359.9 | FW17: 271 | FX17: 1478.1 | FY17: 5220 | FZ17: 293.1 | GA17: 10396.1 | GB17: 5480.2 | GC17: 303.7 | GD17: 1712.4 | GE17: 6245.3 | GF17: 306.2 | GG17: 324.7 | GH17: 3788.4 | GI17: 345.1 | GJ17: 1551.6 | GK17: 3582.8 | GL17: 370.7 | GM17: 10460.1 | GN17: 3630.2 | GO17: 381.5 | GP17: 13388.7 | GQ17: 3663.6 | GR17: 398.2 | GS17: 286.7 | GT17: 3542.5 | GU17: 302.1
A18: Bonds | B18: NLK-Finance | DS18: 2004.8 | FM18: 130.7 | FP18: 128.6 | FQ18: 234.1 | FR18: 263.8 | FS18: 196.8 | FT18: 250.6 | FU18: 662.3 | FV18: 193.6 | FW18: 247.1 | FX18: 652.3 | FY18: 190.9 | FZ18: 243.1 | GA18: 642.7 | GB18: 187.7 | GC18: 239.6 | GD18: 631.2 | GE18: 184.6 | GF18: 235.6 | GG18: 621.5 | GH18: 181.8 | GI18: 231.5 | GJ18: 610.8 | GK18: 178.6 | GL18: 228.1 | GM18: 601 | GN18: 175.5 | GO18: 224.1 | GP18: 591.2 | GQ18: 172.6 | GR18: 220 | GS18: 580.7 | GT18: 169.4 | GU18: 216.5
A19: Bonds | B19: Rosteh | FX19: 134.3 | GD19: 558.2 | GJ19: 558.2 | GP19: 646.4
A20: Bonds | B20: VK | FP20: 897.6 | FV20: 897.6 | GB20: 897.6 | GH20: 897.6 | GN20: 897.6 | GT20: 897.6
A21: Bonds | B21: SibirAirlines | FM21: 1.2
A22: Bonds | B22: UralAirlines | FH22: 0.1 | FN22: 0.1 | FO22: 19.6
A23: Debt obligations of foreign countries | B23: Ukraine | BN23: 4550 | BT23: 4040
A24: Securities | B24: Other RUS issuers | FW24: 2103.9 | FX24: 82.3 | GC24: 4066.6 | GD24: 119.7 | GE24: 1024.2 | GF24: 939.3 | GG24: 570.1 | GH24: 348.8 | GI24: 3653.1 | GJ24: 119.7 | GK24: 809.2 | GL24: 854.1 | GM24: 581.5 | GN24: 344.8 | GO24: 3797.6 | GP24: 119.7 | GQ24: 834.7 | GR24: 858.5 | GS24: 604.1 | GT24: 348.1 | GU24: 3348.1
FW25: plural | GC25: plural | GE25: plural | GF25: plural | GG25: plural | GH25: plural | GI25: plural | GK25: single | GL25: plural | GM25: single | GN25: single | GO25: plural | GP25: single | GQ25: single | GS25: single | GT25: single | GU25: plural
GN26: securities
DX27: # shares | EB27: =EB9-EB28 -> 135.97609 | GB27: CNY %% | GE27: =3000*10.79*0.05/2 -> 809.25 | GF27: =2750*10.79*0.05/2 -> 741.8125 | GK27: =3000*11*0.05/2 -> 825 | GL27: =2750*10.79*0.05/2 -> 741.8125
DU28: Yamal LPG | DV28: RU000A0JVYR5 | DW28: yamal 02 | DX28: =1156206 -> 1156206 | EB28: =1672.56/1000000*DX28 -> 1933.8239 | EH28: =1286.8/1000000*DX28 -> 1487.8059 | EN28: =1205.33/1000000*DX28 -> 1393.6098 | ET28: =1164.4/1000000*DX28 -> 1346.2863 | EZ28: =1010.04/1000000*DX28 -> 1167.8143 | FF28: =(1324.45)/1000000*DX28 -> 1531.337 | FL28: =1632.07*DX28/1000000 -> 1887.0091
DU29: Yamal LPG | DV29: RU000A0JV8S8 | DW29: yamal 01 | DX29: 1207024 | EE29: =1667.97/1000000*DX29 -> 2013.2798 | EK29: =1221/1000000*DX29 -> 1473.7763 | EP29: =1174.25/1000000*DX29 -> 1417.3479 | EV29: =1473.55/1000000*DX29 -> 1778.6102 | FB29: =(1218.14)/1000000*DX29 -> 1470.3242 | FH29: =1427.18/1000000*DX29 -> 1722.6405 | FN29: =DX29*1686.03/1000000 -> 2035.0787
DU30: Yamal LPG | DV30: Principle
DU31: AviaCapital | DV31: RU000A106FE2 | DX31: 17248770 | GM31: =34.16/1000000*DX31 -> 589.21798 | GP31: =3.69/1000000*DX31 -> 63.647961 | GS31: 26.2
DU32: AviaCapital | DV32: RU000A106Q05 | DX32: 67392919 | GO32: =34.16/1000000*DX32 -> 2302.1421
DU33: AviaCapital | DV33: RU000A107EH6 | DX33: 34497540
DU34: AviaCapital | DV34: RU000A106Q13 | DX34: 26680770 | GO34: =34.16/1000000*DX34 -> 911.4151
DU35: AviaCapital | DV35: RU000A106Q39 | DX35: 29569320 | GO35: =34.16/1000000*DX35 -> 1010.088
DU36: Mayak | FX36: 82.3 | GD36: =82.3+37.4 -> 119.7 | GF36: =93.5 -> 93.5 | GI36: =158.6 -> 158.6 | GJ36: =82.3+37.4 -> 119.7 | GL36: =93.5 -> 93.5 | GP36: 119.7
DU37: Atomenergoprom | DV37: RU000A0ZZE61 | DX37: 57500000 | EC37: 144.8
DU38: ZapSibNeftekhim | DV38: RU000A0JVZL5 | DX38: 1750000 | EA38: =1030.97*1750000/1000000 -> 1804.1975 | EG38: =1244.95*1750000/1000000 -> 2178.6625 | EM38: =1212.06*1750000/1000000 -> 2121.105 | ES38: =895.2*1750000/1000000 -> 1566.6
DU39: InfrastructureInvestments-4 | DV39: RU000A0JV3W1 | DX39: 4050000 | ET39: =29.5*DX39/1000000 -> 119.475 | EZ39: =29.5*DX39/1000000 -> 119.475 | FG39: =46.95*DX39/1000000 -> 190.1475 | FL39: =46.95*DX39/1000000 -> 190.1475 | FR39: =64.7*DX39/1000000 -> 262.035 | FX39: =64.7*DX39/1000000 -> 262.035 | GD39: =42.1*DX39/1000000 -> 170.505 | GJ39: =42.1*DX39/1000000 -> 170.505 | GP39: =52.6*DX39/1000000 -> 213.03
GI44: ДОЛЛ | GJ44: РУБ | GK44: ДОЛЛ
GH45: ПОГАШ | GI45: 1943.5 | GJ45: 56685.4 | GK45: =GJ45/GJ48 -> 631.6543
GH46: ВЫДАЧ | GI46: 1875.5 | GJ46: 50583 | GK46: =GJ46/GJ48 -> 563.6543
GH47: РАЗНИЦА | GI47: =GI46-GI45 -> -68 | GJ47: =GJ46-GJ45 -> -6102.4 | GK47: =GK46-GK45 -> -68
GH48: КУРС | GJ48: =GJ47/GI47 -> 89.741176
GI51: номинал до | GJ51: номинал после | GL51: дек 23, $
GG52: выпуск | GH52: RU000A0JVYR5 | GI52: 1000 | GJ52: 823.6 | GL52: 52.78
GG53: кол-во бумаг | GH53: 1156206
GL54: =-GL52*GH53*GJ48/1000000 -> -5476.4152
GL55: =GJ47-GL54 -> -625.98485
GG56: выпуск | GH56: RU000A0JV8S8
GG57: кол-во бумаг | GH57: 1207024

Sheet infra_invest
A1: Год | B1: Месяц | C1: Сумма, млн. руб | D1: Инструмент | E1: Количество | F1: Получатель | G1: Программа
A2: 2026 | B2: Июнь | C2: -0.3 | D2: облигации | F2: ГК «Российские автомобильные дороги» | G2: «Строительство автомобильной дороги М-12 «Строящаяся скоростная автомобильная дорога Москва – Нижний Новгород – Казань» | H2: # | J2: Сумма по полю Сумма, млн. руб | K2: Названия столбцов
A3: 2026 | B3: Июнь | C3: -306.7 | D3: облигации | F3: ГК «Российские автомобильные дороги» | G3: «Строительство автомобильной дороги «Казань – Екатеринбург» на участке Дюртюли – Ачит» | H3: # | J3: Названия строк | K3: облигации | L3: привилегированные акции | M3: (пусто) | N3: Общий итог
A4: 2026 | B4: Июнь | C4: -1020.1 | D4: облигации | F4: ООО «НЛК-Финанс» | H4: # | J4: АО «Атомэнергопром» | L4: 57500 | N4: 57500
A5: 2026 | B5: Июнь | C5: -23.6 | D5: облигации | F5: АО «ГТЛК» | G5: «Программа льготного лизинга гражданских судов водного транспорта» | H5: # | J5: АО «ГТЛК» | K5: 181492.9 | N5: 181492.9
A6: 2026 | B6: Июнь | C6: -188.8 | D6: облигации | F6: АО «ГТЛК» | G6: «Приобретение воздушных судов для последующей передачи в лизинг национальному перевозчику в Дальневосточном федеральном округе»; | H6: # | J6: ГК «Российские автомобильные дороги» | K6: 520430.3 | N6: 520430.3
A7: 2026 | B7: Июнь | C7: -294.5 | D7: облигации | F7: АО «ГТЛК» | G7: «Приобретение вертолетов отечественного производства для последующей передачи в лизинг для нужд российских авиакомпаний» | H7: # | J7: ГК Фонд содействия реформированию жилищно-коммунального хозяйства | K7: 36999.9 | N7: 36999.9
A8: 2026 | B8: Июнь | C8: -655.4 | D8: облигации | F8: АО «ГТЛК» | G8: «Приобретение подвижного состава наземного общественного пассажирского транспорта для последующей передачи в лизинг» | H8: # | J8: ОАО «РЖД» | L8: 255141.3 | N8: 255141.3
A9: 2026 | B9: Июнь | C9: -1718.6 | D9: облигации | F9: ООО «Авиакапитал-Сервис» | G9: «Проект льготного лизинга отечественных воздушных судов» | H9: # | J9: ОАО «Ямал СПГ» | K9: 117247.9 | N9: 117247.9
A10: 2026 | B10: Июнь | C10: 115.5 | D10: облигации | F10: АО «ГТЛК» | G10: «Программа льготного лизинга гражданских судов водного транспорта» | H10: # | J10: ООО «Авиакапитал-Сервис» | K10: 175784.7 | N10: 175784.7
A11: 2026 | B11: Май | C11: -37.8 | D11: облигации | F11: ГК «Российские автомобильные дороги» | G11: «Строительство автомобильной дороги «Казань – Екатеринбург» на участке Дюртюли – Ачит» | H11: # | J11: ООО «ЗапСибНефтехим» | K11: -23202 | N11: -23202
A12: 2026 | B12: Май | C12: -149.3 | D12: облигации | F12: ППК «Фонд развития территорий» | G12: «Программа финансирования строительства, реконструкции и модернизации объектов инфраструктуры за счет средств публично-правовой компании «Фонд развития территорий» | H12: # | J12: ООО «Инфраструктурные инвестиции - 3» | K12: 0 | N12: 0
A13: 2026 | B13: Май | C13: -497.1 | D13: облигации | F13: АО «ГТЛК» | G13: «Приобретение подвижного состава наземного общественного пассажирского транспорта для последующей передачи в лизинг» | H13: # | J13: ООО «Инфраструктурные инвестиции - 4» | K13: 4050 | N13: 4050
A14: 2026 | B14: Май | C14: -804.7 | D14: облигации | F14: ООО «НЛК-Финанс» | H14: # | J14: ППК «Фонд развития территорий» | K14: 112851 | N14: 112851
A15: 2026 | B15: Май | C15: 3159.4 | D15: облигации | F15: АО «ГТЛК» | G15: «Программа льготного лизинга гражданских судов водного транспорта» | H15: # | J15: (пусто)
A16: 2026 | B16: Март | C16: -95.5 | D16: облигации | F16: АО «ГТЛК» | G16: «Приобретение воздушных судов для последующей передачи в лизинг национальному перевозчику в Дальневосточном федеральном округе» | H16: # | J16: ООО «НЛК-Финанс» | K16: -38426.6 | N16: -38426.6
A17: 2026 | B17: Март | C17: -123.7 | D17: облигации | F17: АО «ГТЛК» | G17: «Программа льготного лизинга гражданских судов водного транспорта» | H17: # | J17: ОАО АК «Уральские авиалинии» | K17: -2298.9 | N17: -2298.9
A18: 2026 | B18: Март | C18: -222.8 | D18: облигации | F18: АО «ГТЛК» | G18: «Приобретение вертолетов отечественного производства для последующей передачи в лизинг для нужд российских авиакомпаний» | H18: # | J18: АО «Авиакомпания «Сибирь» | K18: -11851.9 | N18: -11851.9
A19: 2026 | B19: Март | C19: -342.6 | D19: облигации | F19: АО «ГТЛК» | G19: «Приобретение подвижного состава наземного общественного пассажирского транспорта для последующей передачи в лизинг» | H19: # | J19: ГК Ростех | K19: 111093.5 | N19: 111093.5
A20: 2026 | B20: Март | C20: -0.2 | D20: облигации | F20: ГК «Российские автомобильные дороги» | G20: «Строительство автомобильной дороги М-11 «Нева», этап 3 на участке км 149 - км 208 (Обход г. Твери)» | H20: # | J20: Общий итог | K20: 1184170.8 | L20: 312641.3 | N20: 1496812.1
A21: 2026 | B21: Март | C21: -1.2 | D21: облигации | F21: ГК «Российские автомобильные дороги» | G21: «Строительство автомобильной дороги М-12 «Строящаяся скоростная автомобильная дорога Москва – Нижний Новгород – Казань» | H21: #
A22: 2026 | B22: Март | C22: -788.7 | D22: облигации | F22: ГК «Российские автомобильные дороги» | G22: «Строительство автомобильной дороги «Казань – Екатеринбург» на участке Дюртюли – Ачит» | H22: #
A23: 2026 | B23: Март | C23: -969.2 | D23: облигации | F23: ООО «Авиакапитал-Сервис» | H23: #
A24: 2026 | B24: Март | C24: -2666.7 | D24: облигации | F24: ООО «НЛК-Финанс» | H24: #
A25: 2026 | B25: Февраль | C25: -0.4 | D25: облигации | F25: ГК «Российские автомобильные дороги» | G25: «Строительство автомобильной дороги М-12 «Строящаяся скоростная автомобильная дорога Москва – Нижний Новгород – Казань» | H25: #
A26: 2026 | B26: Февраль | C26: -535.5 | D26: облигации | F26: ГК «Российские автомобильные дороги» | G26: «Строительство автомобильной дороги «Казань – Екатеринбург» на участке Дюртюли – Ачит» | H26: #
A27: 2026 | B27: Февраль | C27: -22.6 | D27: облигации | F27: АО «ГТЛК» | G27: «Программа льготного лизинга гражданских судов водного транспорта» | H27: #
A28: 2026 | B28: Февраль | C28: -94.6 | D28: облигации | F28: АО «ГТЛК» | G28: «Приобретение воздушных судов для последующей передачи в лизинг национальному перевозчику в Дальневосточном федеральном округе» | H28: #
A29: 2026 | B29: Февраль | C29: -184.5 | D29: облигации | F29: АО «ГТЛК» | G29: «Приобретение вертолетов отечественного производства для последующей передачи в лизинг для нужд российских авиакомпаний» | H29: #
A30: 2026 | B30: Февраль | C30: -642.1 | D30: облигации | F30: АО «ГТЛК» | G30: «Приобретение подвижного состава наземного общественного пассажирского транспорта для последующей передачи в лизинг» | H30: #
A31: 2026 | B31: Февраль | C31: -1020.1 | D31: облигации | F31: ООО «НЛК-Финанс» | H31: #
A32: 2026 | B32: Февраль | C32: -1718.6 | D32: облигации | F32: ООО «Авиакапитал-Сервис» | G32: «Проект льготного лизинга отечественных воздушных судов» | H32: #
A33: 2026 | B33: Январь | C33: -488.1 | D33: облигации | F33: АО «ГТЛК» | G33: «Приобретение подвижного состава наземного общественного пассажирского транспорта для последующей передачи в лизинг» | H33: #
A34: 2026 | B34: Январь | C34: -804.7 | D34: облигации | F34: ООО «НЛК-Финанс» | H34: #
A35: 2025 | B35: Декабрь | C35: -239.8 | D35: облигации | F35: ООО «Авиакапитал-Сервис» | G35: «Проект льготного лизинга отечественных воздушных судов» | H35: #
A36: 2025 | B36: Декабрь | C36: -94.9 | D36: облигации | F36: АО «ГТЛК» | G36: «Приобретение воздушных судов для последующей передачи в лизинг национальному перевозчику в Дальневосточном федеральном округе» | H36: #
A37: 2025 | B37: Декабрь | C37: -95.7 | D37: облигации | F37: АО «ГТЛК» | G37: «Программа льготного лизинга гражданских судов водного транспорта» | H37: #
A38: 2025 | B38: Декабрь | C38: -221.4 | D38: облигации | F38: АО «ГТЛК» | G38: «Приобретение вертолетов отечественного производства для последующей передачи в лизинг для нужд российских авиакомпаний» | H38: #
A39: 2025 | B39: Декабрь | C39: -340.1 | D39: облигации | F39: АО «ГТЛК» | G39: «Приобретение подвижного состава наземного общественного пассажирского транспорта для последующей передачи в лизинг» | H39: #
A40: 2025 | B40: Декабрь | C40: -0.1 | D40: облигации | F40: ГК «Российские автомобильные дороги» | G40: «Строительство автомобильной дороги М-11 «Нева», этап 3 на участке км 149 - км 208 (Обход г. Твери)» | H40: #
A41: 2025 | B41: Декабрь | C41: -1.2 | D41: облигации | F41: ГК «Российские автомобильные дороги» | G41: «Строительство автомобильной дороги М-12 «Строящаяся скоростная автомобильная дорога Москва – Нижний Новгород – Казань» | H41: #
A42: 2025 | B42: Декабрь | C42: -3391.9 | D42: облигации | F42: ГК «Российские автомобильные дороги» | G42: «Строительство автомобильной дороги «Казань – Екатеринбург» на участке Дюртюли – Ачит» | H42: #
A43: 2025 | B43: Декабрь | C43: -2666.7 | D43: облигации | F43: ООО «НЛК-Финанс» | H43: #
A44: 2025 | B44: Декабрь | C44: 2002.7 | D44: облигации | F44: ППК «Фонд развития территорий» | G44: «Программа финансирования строительства, реконструкции и модернизации объектов инфраструктуры за счет средств публично-правовой компании «Фонд развития территорий», полученных из средств Фонда национального благосостояния» | H44: #
A45: 2025 | B45: Декабрь | C45: 7000 | D45: облигации | F45: ООО «Авиакапитал-Сервис» | H45: #
A46: 2025 | B46: Ноябрь | C46: -1718.6 | D46: облигации | F46: ООО «Авиакапитал-Сервис» | G46: «Проект льготного лизинга отечественных воздушных судов» | H46: #
A47: 2025 | B47: Ноябрь | C47: -16.2 | D47: облигации | F47: АО «ГТЛК» | G47: «Программа льготного лизинга гражданских судов водного транспорта» | H47: #
A48: 2025 | B48: Ноябрь | C48: -52 | D48: облигации | F48: АО «ГТЛК» | G48: «Приобретение воздушных судов для последующей передачи в лизинг национальному перевозчику в Дальневосточном федеральном округе» | H48: #
A49: 2025 | B49: Ноябрь | C49: -184.1 | D49: облигации | F49: АО «ГТЛК» | G49: «Приобретение вертолетов отечественного производства для последующей передачи в лизинг для нужд российских авиакомпаний» | H49: #
A50: 2025 | B50: Ноябрь | C50: -634.1 | D50: облигации | F50: АО «ГТЛК» | G50: «Приобретение подвижного состава наземного общественного пассажирского транспорта для последующей передачи в лизинг» | H50: #
A51: 2025 | B51: Ноябрь | C51: -0.4 | D51: облигации | F51: ГК «Российские автомобильные дороги» | G51: «Строительство автомобильной дороги М-12 «Строящаяся скоростная автомобильная дорога Москва – Нижний Новгород – Казань» | H51: #
A52: 2025 | B52: Ноябрь | C52: -306.6 | D52: облигации | F52: ГК «Российские автомобильные дороги» | G52: «Строительство автомобильной дороги «Казань – Екатеринбург» на участке Дюртюли – Ачит» | H52: #
A53: 2025 | B53: Ноябрь | C53: -1020.1 | D53: облигации | F53: ООО «НЛК-Финанс» | H53: #
A54: 2025 | B54: Ноябрь | C54: 1228.1 | D54: облигации | F54: ППК «Фонд развития территорий» | G54: «Программа финансирования строительства, реконструкции и модернизации объектов инфраструктуры за счет средств публично-правовой компании «Фонд развития территорий», полученных из средств Фонда национального благосостояния» | H54: #
A55: 2025 | B55: Октябрь | C55: -482.4 | D55: облигации | F55: АО «ГТЛК» | G55: «Приобретение подвижного состава наземного общественного пассажирского транспорта для последующей передачи в лизинг» | H55: #
A56: 2025 | B56: Октябрь | C56: -37.8 | D56: облигации | F56: ГК «Российские автомобильные дороги» | G56: «Строительство автомобильной дороги «Казань – Екатеринбург» на участке Дюртюли – Ачит» | H56: #
A57: 2025 | B57: Октябрь | C57: -804.7 | D57: облигации | F57: ООО «НЛК-Финанс» | H57: #
A58: 2025 | B58: Октябрь | C58: 347.3 | D58: облигации | F58: ППК «Фонд развития территорий» | G58: «Программа финансирования строительства, реконструкции и модернизации объектов инфраструктуры за счет средств публично-правовой компании «Фонд развития территорий», полученных из средств Фонда национального благосостояния» | H58: #
A59: 2025 | B59: Октябрь | C59: 426.4 | D59: облигации | F59: АО «ГТЛК» | G59: «Программа льготного лизинга гражданских судов водного транспорта» | H59: #
A60: 2025 | B60: Сентябрь | C60: -239.8 | D60: облигации | F60: ООО «Авиакапитал-Сервис» | H60: #
A61: 2025 | B61: Сентябрь | C61: -94.3 | D61: облигации | F61: АО «ГТЛК» | G61: «Приобретение воздушных судов для последующей передачи в лизинг национальному перевозчику в Дальневосточном федеральном округе» | H61: #
A62: 2025 | B62: Сентябрь | C62: -52.1 | D62: облигации | F62: АО «ГТЛК» | G62: «Программа льготного лизинга гражданских судов водного транспорта» | H62: #
A63: 2025 | B63: Сентябрь | C63: -220 | D63: облигации | F63: АО «ГТЛК» | G63: «Приобретение вертолетов отечественного производства для последующей передачи в лизинг для нужд российских авиакомпаний» | H63: #
A64: 2025 | B64: Сентябрь | C64: -331.3 | D64: облигации | F64: АО «ГТЛК» | G64: «Приобретение подвижного состава наземного общественного пассажирского транспорта для последующей передачи в лизинг» | H64: #
A65: 2025 | B65: Сентябрь | C65: -0.1 | D65: облигации | F65: ГК «Российские автомобильные дороги» | G65: «Строительство автомобильной дороги М-11 «Нева», этап 3 на участке км 149 - км 208 (Обход г. Твери)» | H65: #
A66: 2025 | B66: Сентябрь | C66: -1.1 | D66: облигации | F66: ГК «Российские автомобильные дороги» | G66: «Строительство автомобильной дороги М-12 «Строящаяся скоростная автомобильная дорога Москва – Нижний Новгород – Казань» | H66: #
A67: 2025 | B67: Сентябрь | C67: -788.7 | D67: облигации | F67: ГК «Российские автомобильные дороги» | G67: «Строительство автомобильной дороги «Казань – Екатеринбург» на участке Дюртюли – Ачит» | H67: #
A68: 2025 | B68: Сентябрь | C68: -2666.7 | D68: облигации | F68: ООО «НЛК-Финанс» | H68: #
A69: 2025 | B69: Сентябрь | C69: 156.9 | D69: облигации | F69: ППК «Фонд развития территорий» | G69: «Программа финансирования строительства, реконструкции и модернизации объектов инфраструктуры за счет средств публично-правовой компании «Фонд развития территорий», полученных из средств Фонда национального благосостояния» | H69: #
A70: 2025 | B70: Август | C70: -0.4 | D70: облигации | F70: ГК «Российские автомобильные дороги» | G70: «Строительство автомобильной дороги М-12 «Строящаяся скоростная автомобильная дорога Москва – Нижний Новгород – Казань» | H70: #
A71: 2025 | B71: Август | C71: -535.5 | D71: облигации | F71: ГК «Российские автомобильные дороги» | G71: «Строительство автомобильной дороги «Казань – Екатеринбург» на участке Дюртюли – Ачит» | H71: #
A72: 2025 | B72: Август | C72: -2.2 | D72: облигации | F72: АО «ГТЛК» | G72: «Программа льготного лизинга гражданских судов водного транспорта» | H72: #
A73: 2025 | B73: Август | C73: -181.3 | D73: облигации | F73: АО «ГТЛК» | G73: «Приобретение вертолетов отечественного производства для последующей передачи в лизинг для нужд российских авиакомпаний» | H73: #
A74: 2025 | B74: Август | C74: -622.7 | D74: облигации | F74: АО «ГТЛК» | G74: «Приобретение подвижного состава наземного общественного пассажирского транспорта для последующей передачи в лизинг» | H74: #
A75: 2025 | B75: Август | C75: -1020.1 | D75: облигации | F75: ООО «НЛК-Финанс»
A76: 2025 | B76: Август | C76: 1230.9 | D76: облигации | F76: ППК «Фонд развития территорий» | G76: «Программа финансирования строительства, реконструкции и модернизации объектов инфраструктуры за счет средств публично-правовой компании «Фонд развития территорий», полученных из средств Фонда национального благосостояния» | H76: #
A77: 2025 | B77: Июль | C77: -474.1 | D77: облигации | F77: АО «ГТЛК» | G77: «Приобретение подвижного состава наземного общественного пассажирского транспорта для последующей передачи в лизинг» | H77: #
A78: 2025 | B78: Июль | C78: -804.7 | D78: облигации | F78: ООО «НЛК-Финанс»
A79: 2025 | B79: Июнь | C79: -1.2 | D79: облигации | F79: ГК «Российские автомобильные дороги» | G79: «Строительство автомобильной дороги М-12 «Строящаяся скоростная автомобильная дорога Москва – Нижний Новгород – Казань» | H79: #
A80: 2025 | B80: Июнь | C80: -15.8 | D80: облигации | F80: АО «ГТЛК» | G80: «Программа льготного лизинга гражданских судов водного транспорта» | H80: #
A81: 2025 | B81: Июнь | C81: -76.2 | D81: облигации | F81: АО «ГТЛК» | G81: «Приобретение воздушных судов для последующей передачи в лизинг национальному перевозчику в Дальневосточном федеральном округе» | H81: #
A82: 2025 | B82: Июнь | C82: -178.4 | D82: облигации | F82: АО «ГТЛК» | G82: «Приобретение вертолетов отечественного производства для последующей передачи в лизинг для нужд российских авиакомпаний» | H82: #
A83: 2025 | B83: Июнь | C83: -326.3 | D83: облигации | F83: АО «ГТЛК» | G83: «Приобретение подвижного состава наземного общественного пассажирского транспорта для последующей передачи в лизинг» | H83: #
A84: 2025 | B84: Июнь | C84: -2666.7 | D84: облигации | F84: ООО «НЛК-Финанс»
A85: 2025 | B85: Июнь | C85: 3371.7 | D85: облигации | F85: АО «ГТЛК» | G85: «Программа льготного лизинга гражданских судов водного транспорта» | H85: #
A86: 2025 | B86: Май | C86: -0.4 | D86: облигации | F86: ГК «Российские автомобильные дороги» | G86: «Строительство автомобильной дороги М-12 «Строящаяся скоростная автомобильная дорога Москва – Нижний Новгород – Казань» | H86: #
A87: 2025 | B87: Май | C87: -180.1 | D87: облигации | F87: АО «ГТЛК» | G87: «Приобретение вертолетов отечественного производства для последующей передачи в лизинг для нужд российских авиакомпаний» | H87: #
A88: 2025 | B88: Май | C88: -612.1 | D88: облигации | F88: АО «ГТЛК» | G88: «Приобретение подвижного состава наземного общественного пассажирского транспорта для последующей передачи в лизинг» | H88: #
A89: 2025 | B89: Май | C89: -1020.1 | D89: облигации | F89: ООО «НЛК-Финанс»
A90: 2025 | B90: Май | C90: 660.2 | D90: облигации | F90: ППК «Фонд развития территорий» | G90: «Программа финансирования строительства, реконструкции и модернизации объектов инфраструктуры за счет средств публично-правовой компании «Фонд развития территорий» | H90: #
A91: 2025 | B91: Май | C91: 6579.2 | D91: облигации | F91: АО «ГТЛК» | G91: «Приобретение воздушных судов для последующей передачи в лизинг национальному перевозчику в Дальневосточном федеральном округе» | H91: #
A92: 2025 | B92: Апрель | C92: -464.4 | D92: облигации | F92: АО «ГТЛК» | G92: «Приобретение подвижного состава наземного общественного пассажирского транспорта для последующей передачи в лизинг» | H92: #
A93: 2025 | B93: Апрель | C93: -804.7 | D93: облигации | F93: ООО «НЛК-Финанс»
A94: 2025 | B94: Апрель | C94: 374 | D94: облигации | F94: ППК «Фонд развития территорий» | G94: «Программа финансирования строительства, реконструкции и модернизации объектов инфраструктуры за счет средств публично-правовой компании «Фонд развития территорий» | H94: #
A95: 2025 | B95: Март | C95: -1.2 | D95: облигации | F95: ГК «Российские автомобильные дороги» | G95: «Строительство автомобильной дороги М-12 «Строящаяся скоростная автомобильная дорога Москва – Нижний Новгород – Казань» | H95: #
A96: 2025 | B96: Март | C96: -5.9 | D96: облигации | F96: АО «ГТЛК» | G96: «Программа льготного лизинга гражданских судов водного транспорта» | H96: #
A97: 2025 | B97: Март | C97: -128.2 | D97: облигации | F97: АО «ГТЛК» | G97: «Приобретение подвижного состава наземного общественного пассажирского транспорта для последующей передачи в лизинг» | H97: #
A98: 2025 | B98: Март | C98: -2666.7 | D98: облигации | F98: ООО «НЛК-Финанс» | H98: #
A99: 2025 | B99: Март | C99: 2563 | D99: облигации | F99: АО «ГТЛК» | G99: «Программа льготного лизинга гражданских судов водного транспорта» | H99: #
A100: 2025 | B100: Февраль | C100: -0.4 | D100: облигации | F100: ГК «Российские автомобильные дороги» | G100: «Строительство автомобильной дороги М-12 «Строящаяся скоростная автомобильная дорога Москва – Нижний Новгород – Казань» | H100: #
...

Sheet projects
A1: Проект | B1: Общий объем, млн руб | C1: Объем ФНБ, млн. руб | D1: Профинансировано, млн. руб. | E1: Доля профинансированного | F1: Осталось профинансировать | G1: Срок реализации проекта | H1: К финансированию в 2025 г | I1: Участники | J1: Иные ссылки | K1: Программа
A2: СПГ-завод в составе КПЭГ в Усть-Луге | B2: 4915000 | C2: 900000 | D2: =Main_!AK23+Main_!AK25+Main_!AP40 -> 771347 | E2: =D2/C2 -> 0.85705222 | F2: =C2-D2 -> 128653 | G2: 2021-2027 | H2: =213000-(Main_!AK23-Main_!AD23) -> 1367 | I2: ООО «РусХимАльянс» (ПАО «Газпром» и АО «РусГаздобыча»), ООО «Балтийский Химический Комплекс» (АО «РусГаздобыча») | J2: Neftegaz.RU | K2: Программа
A3: Ростех | K3: Программа
A4: Ж/Д Москва - СПб | B4: 2165514 | C4: 300000 | D4: =Main_!AI35+Main_!AI36+Main_!AI37+Main_!AI39 -> 300000 | E4: =D4/C4 -> 1 | F4: =C4-D4 -> 0 | G4: 2024-2027 | H4: =300000-D4 -> 0 | I4: ООО "ВСМ Две Столиы" | K4: Программа

Sheet %% Усть-Луга
A1: Расчет капитализации проентов по Усть-Луге
A2: 1 | B2: 2 | C2: 3 | D2: 4 | E2: 5 | F2: 6 | G2: 7 | H2: 8 | I2: 9 | J2: 10 | K2: 11 | L2: 12 | M2: 13 | N2: 14 | O2: 15 | P2: 16 | Q2: 17 | R2: 18 | S2: 19 | T2: 20 | U2: 21 | V2: 22 | W2: 23 | X2: 24 | Y2: 25 | Z2: 26 | AA2: 27 | AB2: 28 | AC2: 29 | AD2: 30 | AE2: 31 | AF2: 32 | AG2: 33 | AH2: 34 | AI2: 35 | AJ2: 36 | AK2: 37 | AL2: 38 | AM2: 39 | AN2: 40 | AO2: 41 | AP2: 42 | AQ2: 43 | AR2: 44 | AS2: 45 | AT2: 46 | AU2: 47 | AV2: 48 | AW2: 49 | AX2: 50 | AY2: 51 | AZ2: 52 | BA2: 53 | BB2: 54 | BC2: 55 | BD2: 56 | BE2: 57 | BF2: 58 | BG2: 59 | BH2: 60
A3: 01.05.2024 | B3: 01.06.2024 | C3: 01.07.2024 | D3: 01.08.2024 | E3: 01.09.2024 | F3: 01.10.2024 | G3: 01.11.2024 | H3: 01.12.2024 | I3: 01.01.2025 | J3: 01.02.2025 | K3: 01.03.2025 | L3: 01.04.2025 | M3: 01.05.2025 | N3: 01.06.2025 | O3: 01.07.2025 | P3: 01.08.2025 | Q3: 01.09.2025 | R3: 01.10.2025 | S3: 01.11.2025 | T3: 01.12.2025 | U3: 01.01.2026
A4: 20 | B4: 31 | C4: 30 | D4: 31 | E4: 31 | F4: 30 | G4: 31 | H4: 30 | I4: 31 | J4: 31 | K4: 28 | L4: 30 | M4: 30 | N4: 30 | O4: 30 | P4: 30 | Q4: 30 | R4: 30 | S4: 30 | T4: 30 | U4: 30 | V4: 30 | W4: 30 | X4: 30 | Y4: 30 | Z4: 30 | AA4: 30 | AB4: 30 | AC4: 30 | AD4: 30 | AE4: 30 | AF4: 30 | AG4: 30 | AH4: 30 | AI4: 30 | AJ4: 30 | AK4: 30 | AL4: 30 | AM4: 30 | AN4: 30 | AO4: 30 | AP4: 30 | AQ4: 30 | AR4: 30 | AS4: 30 | AT4: 30 | AU4: 30 | AV4: 30 | AW4: 30 | AX4: 30 | AY4: 30 | AZ4: 30 | BA4: 30 | BB4: 30 | BC4: 30 | BD4: 30 | BE4: 30 | BF4: 30 | BG4: 30 | BH4: 30
A5: =Main_!V23 -> 316 | B5: =Main_!W23 -> 316 | C5: =Main_!X23 -> 316 | D5: =Main_!Y23 -> 27201 | E5: =Main_!Z23 -> 27201 | F5: =Main_!AA23 -> 27201 | G5: =Main_!AB23 -> 89251 | H5: =Main_!AC23 -> 89251 | ... U5: =Main_!AP23 -> 440000
A6: 0.06 | B6: 0.06 | C6: 0.06 | D6: 0.06 | E6: 0.06 | F6: 0.06 | G6: 0.06 | H6: 0.06 | I6: 0.06 | J6: 0.06 | K6: 0.06 | L6: 0.06 | M6: 0.06 | N6: 0.06 | O6: 0.06 | P6: 0.06 | Q6: 0.06 | R6: 0.06 | S6: 0.06 | T6: 0.06 | U6: 0.06 | V6: 0.06 | W6: 0.06 | X6: 0.06 | Y6: 0.06 | Z6: 0.06 | AA6: 0.06 | AB6: 0.06 | AC6: 0.06 | AD6: 0.06 | AE6: 0.06 | AF6: 0.06 | AG6: 0.06 | AH6: 0.06 | AI6: 0.06 | AJ6: 0.06 | AK6: 0.06 | AL6: 0.06 | AM6: 0.06 | AN6: 0.06 | AO6: 0.06 | AP6: 0.06 | AQ6: 0.06 | AR6: 0.06 | AS6: 0.06 | AT6: 0.06 | AU6: 0.06 | AV6: 0.06 | AW6: 0.06 | AX6: 0.06 | AY6: 0.06 | AZ6: 0.06 | BA6: 0.06 | BB6: 0.06 | BC6: 0.06 | BD6: 0.06 | BE6: 0.06 | BF6: 0.06 | BG6: 0.06 | BH6: 0.06
A7: =A5*A6*A4/365 -> 1.0389041 | B7: =B5*B6*B4/365 -> 1.6103014 | C7: =C5*C6*C4/365 -> 1.5583562 | D7: =D5*D6*D4/365 -> 138.61332 | E7: =E5*E6*E4/365 -> 138.61332 | F7: =F5*F6*F4/365 -> 134.14192 | G7: =G5*G6*G4/365 -> 454.81332 | H7: =H5*H6*H4/365 -> 440.14192 | ... BH7: =BH5*BH6*BH4/365 -> 0
A8: кумулятивный
B9: =A7 -> 1.0389041 | C9: =B9+B7 -> 2.6492055 | D9: =C9+C7 -> 4.2075616 | E9: =D9+D7 -> 142.82088 | F9: =E9+E7 -> 281.43419 | G9: =F9+F7 -> 415.57611 | H9: =G9+G7 -> 870.38942 | I9: =H9+H7 -> 1310.5313 | J9: =I9+I7 -> 2463.6804 | ... BH9: =BG9+BG7 -> 26723.289
